{
"meta":{"test_sets":[],"test_metrics":[],"learn_metrics":[{"best_value":"Min","name":"RMSE"}],"launch_mode":"Train","parameters":"","iteration_count":1000,"learn_sets":["learn"],"name":"experiment"},
"iterations":[
{"learn":[0.3974929293],"iteration":0,"passed_time":0.00191008841,"remaining_time":1.908178322},
{"learn":[0.3878235937],"iteration":1,"passed_time":0.003467117664,"remaining_time":1.730091714},
{"learn":[0.378216104],"iteration":2,"passed_time":0.004958568912,"remaining_time":1.647897735},
{"learn":[0.3686401208],"iteration":3,"passed_time":0.006429219558,"remaining_time":1.60087567},
{"learn":[0.3586546512],"iteration":4,"passed_time":0.007872075952,"remaining_time":1.566543114},
{"learn":[0.3491537847],"iteration":5,"passed_time":0.00929260877,"remaining_time":1.53947552},
{"learn":[0.3404466971],"iteration":6,"passed_time":0.01090410785,"remaining_time":1.546825585},
{"learn":[0.3322217805],"iteration":7,"passed_time":0.01246760973,"remaining_time":1.545983607},
{"learn":[0.3240213332],"iteration":8,"passed_time":0.01402293566,"remaining_time":1.544081027},
{"learn":[0.3161710882],"iteration":9,"passed_time":0.01550265401,"remaining_time":1.534762747},
{"learn":[0.30915147],"iteration":10,"passed_time":0.01699167051,"remaining_time":1.527705648},
{"learn":[0.3017255355],"iteration":11,"passed_time":0.01851929236,"remaining_time":1.524755071},
{"learn":[0.2947050064],"iteration":12,"passed_time":0.02002045256,"remaining_time":1.52001436},
{"learn":[0.2876049669],"iteration":13,"passed_time":0.02149593263,"remaining_time":1.513927827},
{"learn":[0.2820627212],"iteration":14,"passed_time":0.02296135307,"remaining_time":1.507795518},
{"learn":[0.2762873487],"iteration":15,"passed_time":0.02445642138,"remaining_time":1.504069915},
{"learn":[0.2700019473],"iteration":16,"passed_time":0.02600593596,"remaining_time":1.503755003},
{"learn":[0.2638390202],"iteration":17,"passed_time":0.02756953805,"remaining_time":1.504071464},
{"learn":[0.2588264801],"iteration":18,"passed_time":0.02910803112,"remaining_time":1.502893607},
{"learn":[0.2534827804],"iteration":19,"passed_time":0.03060662631,"remaining_time":1.499724689},
{"learn":[0.2483804395],"iteration":20,"passed_time":0.03212592191,"remaining_time":1.497679883},
{"learn":[0.2436159562],"iteration":21,"passed_time":0.03364789273,"remaining_time":1.495801777},
{"learn":[0.2382873471],"iteration":22,"passed_time":0.03524726464,"remaining_time":1.497242502},
{"learn":[0.2338474667],"iteration":23,"passed_time":0.03680246031,"remaining_time":1.496633386},
{"learn":[0.2293140289],"iteration":24,"passed_time":0.03837375741,"remaining_time":1.496576539},
{"learn":[0.224964077],"iteration":25,"passed_time":0.03993925319,"remaining_time":1.49618587},
{"learn":[0.2209449334],"iteration":26,"passed_time":0.04152573995,"remaining_time":1.496464628},
{"learn":[0.2169083267],"iteration":27,"passed_time":0.04335399863,"remaining_time":1.505003095},
{"learn":[0.2132926205],"iteration":28,"passed_time":0.04496669655,"remaining_time":1.505609046},
{"learn":[0.2095418346],"iteration":29,"passed_time":0.04661179771,"remaining_time":1.507114793},
{"learn":[0.2063549766],"iteration":30,"passed_time":0.04822454222,"remaining_time":1.507405852},
{"learn":[0.2032117159],"iteration":31,"passed_time":0.04983386355,"remaining_time":1.507474372},
{"learn":[0.2000340436],"iteration":32,"passed_time":0.05141434858,"remaining_time":1.506596215},
{"learn":[0.1969534323],"iteration":33,"passed_time":0.05289311507,"remaining_time":1.50278674},
{"learn":[0.194051674],"iteration":34,"passed_time":0.05442993488,"remaining_time":1.500711062},
{"learn":[0.1910017595],"iteration":35,"passed_time":0.05588258038,"remaining_time":1.496411319},
{"learn":[0.1880118546],"iteration":36,"passed_time":0.05734319143,"remaining_time":1.492472793},
{"learn":[0.1853091135],"iteration":37,"passed_time":0.05892766425,"remaining_time":1.491800342},
{"learn":[0.18257851],"iteration":38,"passed_time":0.06052269769,"remaining_time":1.491341346},
{"learn":[0.1800883282],"iteration":39,"passed_time":0.06198864916,"remaining_time":1.48772758},
{"learn":[0.1774247575],"iteration":40,"passed_time":0.06352131085,"remaining_time":1.485778954},
{"learn":[0.1752146248],"iteration":41,"passed_time":0.06504155831,"remaining_time":1.483566973},
{"learn":[0.1731175907],"iteration":42,"passed_time":0.06652930232,"remaining_time":1.480663775},
{"learn":[0.1711993335],"iteration":43,"passed_time":0.06798996347,"remaining_time":1.477236479},
{"learn":[0.1692310139],"iteration":44,"passed_time":0.06948734629,"remaining_time":1.474675905},
{"learn":[0.167278497],"iteration":45,"passed_time":0.07097152334,"remaining_time":1.47188768},
{"learn":[0.1651302451],"iteration":46,"passed_time":0.07255424625,"remaining_time":1.471153121},
{"learn":[0.1631084357],"iteration":47,"passed_time":0.07410673664,"remaining_time":1.46978361},
{"learn":[0.1614680454],"iteration":48,"passed_time":0.07564795504,"remaining_time":1.468187862},
{"learn":[0.1598671386],"iteration":49,"passed_time":0.07715802262,"remaining_time":1.46600243},
{"learn":[0.1583727577],"iteration":50,"passed_time":0.07866533483,"remaining_time":1.463792211},
{"learn":[0.156868963],"iteration":51,"passed_time":0.08021611188,"remaining_time":1.462401424},
{"learn":[0.1554213324],"iteration":52,"passed_time":0.08173464599,"remaining_time":1.460428486},
{"learn":[0.1539214845],"iteration":53,"passed_time":0.08330296729,"remaining_time":1.459344575},
{"learn":[0.1525381622],"iteration":54,"passed_time":0.08481288458,"remaining_time":1.457239562},
{"learn":[0.1511891649],"iteration":55,"passed_time":0.08638344024,"remaining_time":1.456177993},
{"learn":[0.1499850665],"iteration":56,"passed_time":0.08807244711,"remaining_time":1.457058204},
{"learn":[0.1487268017],"iteration":57,"passed_time":0.08966948445,"remaining_time":1.45635611},
{"learn":[0.147736901],"iteration":58,"passed_time":0.09123538102,"remaining_time":1.455127009},
{"learn":[0.1464918366],"iteration":59,"passed_time":0.09276063825,"remaining_time":1.453249999},
{"learn":[0.1453576305],"iteration":60,"passed_time":0.0942239145,"remaining_time":1.450430422},
{"learn":[0.1442038095],"iteration":61,"passed_time":0.09571353217,"remaining_time":1.448053116},
{"learn":[0.1430399305],"iteration":62,"passed_time":0.09725967017,"remaining_time":1.446544618},
{"learn":[0.1421026601],"iteration":63,"passed_time":0.09873947869,"remaining_time":1.444064876},
{"learn":[0.141004088],"iteration":64,"passed_time":0.1002569507,"remaining_time":1.442157676},
{"learn":[0.1400195654],"iteration":65,"passed_time":0.1017568685,"remaining_time":1.440013866},
{"learn":[0.1389252106],"iteration":66,"passed_time":0.1033333157,"remaining_time":1.438954978},
{"learn":[0.1379504347],"iteration":67,"passed_time":0.1048654062,"remaining_time":1.437272921},
{"learn":[0.1368914616],"iteration":68,"passed_time":0.1064218644,"remaining_time":1.435923996},
{"learn":[0.1360549106],"iteration":69,"passed_time":0.1079590749,"remaining_time":1.434313424},
{"learn":[0.1352373054],"iteration":70,"passed_time":0.1095164749,"remaining_time":1.432969087},
{"learn":[0.1343757261],"iteration":71,"passed_time":0.1110862691,"remaining_time":1.431778579},
{"learn":[0.1336340465],"iteration":72,"passed_time":0.1127518603,"remaining_time":1.431794171},
{"learn":[0.1328450889],"iteration":73,"passed_time":0.1142803839,"remaining_time":1.430049128},
{"learn":[0.1320019793],"iteration":74,"passed_time":0.1158000602,"remaining_time":1.428200743},
{"learn":[0.1311530748],"iteration":75,"passed_time":0.1172863814,"remaining_time":1.42595548},
{"learn":[0.130535634],"iteration":76,"passed_time":0.1189445782,"remaining_time":1.425790203},
{"learn":[0.1297255568],"iteration":77,"passed_time":0.1204444559,"remaining_time":1.423715235},
{"learn":[0.1290491956],"iteration":78,"passed_time":0.1219834499,"remaining_time":1.422110853},
{"learn":[0.1284627585],"iteration":79,"passed_time":0.1235471322,"remaining_time":1.42079202},
{"learn":[0.1278197143],"iteration":80,"passed_time":0.1250621494,"remaining_time":1.418915004},
{"learn":[0.1270850293],"iteration":81,"passed_time":0.1265467373,"remaining_time":1.416706156},
{"learn":[0.1264472387],"iteration":82,"passed_time":0.1280277481,"remaining_time":1.414475241},
{"learn":[0.1256897146],"iteration":83,"passed_time":0.1295050417,"remaining_time":1.412221646},
{"learn":[0.1250915802],"iteration":84,"passed_time":0.1309702117,"remaining_time":1.409855808},
{"learn":[0.1245158022],"iteration":85,"passed_time":0.1324874132,"remaining_time":1.408063903},
{"learn":[0.1239482136],"iteration":86,"passed_time":0.1341132668,"remaining_time":1.407418535},
{"learn":[0.123196236],"iteration":87,"passed_time":0.1356384138,"remaining_time":1.405707198},
{"learn":[0.1225285133],"iteration":88,"passed_time":0.1371485616,"remaining_time":1.403846512},
{"learn":[0.1218083946],"iteration":89,"passed_time":0.138658048,"remaining_time":1.40198693},
{"learn":[0.1212331067],"iteration":90,"passed_time":0.1401708409,"remaining_time":1.40016807},
{"learn":[0.1206441043],"iteration":91,"passed_time":0.1416502086,"remaining_time":1.398025972},
{"learn":[0.1200853535],"iteration":92,"passed_time":0.1431216307,"remaining_time":1.395820635},
{"learn":[0.1195863022],"iteration":93,"passed_time":0.1445773122,"remaining_time":1.3934792},
{"learn":[0.1189758313],"iteration":94,"passed_time":0.1460251383,"remaining_time":1.39108158},
{"learn":[0.1185034508],"iteration":95,"passed_time":0.1474632253,"remaining_time":1.388612039},
{"learn":[0.1179745646],"iteration":96,"passed_time":0.1490167177,"remaining_time":1.387238104},
{"learn":[0.1175137888],"iteration":97,"passed_time":0.1504838214,"remaining_time":1.385065377},
{"learn":[0.1171204765],"iteration":98,"passed_time":0.1520063734,"remaining_time":1.383411539},
{"learn":[0.1165953389],"iteration":99,"passed_time":0.1535034857,"remaining_time":1.381531371},
{"learn":[0.1161464523],"iteration":100,"passed_time":0.1550015198,"remaining_time":1.379666993},
{"learn":[0.1157072124],"iteration":101,"passed_time":0.1566362407,"remaining_time":1.379013178},
{"learn":[0.1152345579],"iteration":102,"passed_time":0.1582298613,"remaining_time":1.377982385},
{"learn":[0.114831422],"iteration":103,"passed_time":0.1599143193,"remaining_time":1.377723367},
{"learn":[0.1143590995],"iteration":104,"passed_time":0.1614670001,"remaining_time":1.376313953},
{"learn":[0.1139736413],"iteration":105,"passed_time":0.1631676196,"remaining_time":1.376149547},
{"learn":[0.1134846616],"iteration":106,"passed_time":0.1646732285,"remaining_time":1.374328907},
{"learn":[0.1130393865],"iteration":107,"passed_time":0.1662075234,"remaining_time":1.372751027},
{"learn":[0.1126900512],"iteration":108,"passed_time":0.1676720421,"remaining_time":1.370603573},
{"learn":[0.1123185385],"iteration":109,"passed_time":0.1692715543,"remaining_time":1.369560757},
{"learn":[0.1120313989],"iteration":110,"passed_time":0.1710634084,"remaining_time":1.370048379},
{"learn":[0.1116816116],"iteration":111,"passed_time":0.1726433158,"remaining_time":1.368814861},
{"learn":[0.1112821872],"iteration":112,"passed_time":0.1741674007,"remaining_time":1.367137031},
{"learn":[0.1108777696],"iteration":113,"passed_time":0.1757646485,"remaining_time":1.366030514},
{"learn":[0.1105087779],"iteration":114,"passed_time":0.1774278049,"remaining_time":1.365422672},
{"learn":[0.1101694165],"iteration":115,"passed_time":0.1790063061,"remaining_time":1.364151505},
{"learn":[0.1098279195],"iteration":116,"passed_time":0.1808622588,"remaining_time":1.364969013},
{"learn":[0.1094550422],"iteration":117,"passed_time":0.1824792952,"remaining_time":1.36395541},
{"learn":[0.1091868449],"iteration":118,"passed_time":0.1839880602,"remaining_time":1.362130093},
{"learn":[0.1088299454],"iteration":119,"passed_time":0.1856149959,"remaining_time":1.361176637},
{"learn":[0.1085561242],"iteration":120,"passed_time":0.1871366962,"remaining_time":1.35944757},
{"learn":[0.1082058852],"iteration":121,"passed_time":0.188749334,"remaining_time":1.358376355},
{"learn":[0.1078485398],"iteration":122,"passed_time":0.1902638703,"remaining_time":1.356596864},
{"learn":[0.1074942183],"iteration":123,"passed_time":0.1920162008,"remaining_time":1.356501548},
{"learn":[0.1072868962],"iteration":124,"passed_time":0.193641343,"remaining_time":1.355489401},
{"learn":[0.1069991407],"iteration":125,"passed_time":0.1951974805,"remaining_time":1.353988873},
{"learn":[0.1067947],"iteration":126,"passed_time":0.1967935725,"remaining_time":1.352762117},
{"learn":[0.1065200352],"iteration":127,"passed_time":0.198323018,"remaining_time":1.35107556},
{"learn":[0.1062563933],"iteration":128,"passed_time":0.1998507901,"remaining_time":1.349380141},
{"learn":[0.1060588936],"iteration":129,"passed_time":0.2012954801,"remaining_time":1.34713129},
{"learn":[0.105813649],"iteration":130,"passed_time":0.2027671126,"remaining_time":1.345073442},
{"learn":[0.1055795162],"iteration":131,"passed_time":0.2042299079,"remaining_time":1.342966364},
{"learn":[0.1053300897],"iteration":132,"passed_time":0.2057570288,"remaining_time":1.341288301},
{"learn":[0.1051887134],"iteration":133,"passed_time":0.20721771,"remaining_time":1.339183111},
{"learn":[0.1048845603],"iteration":134,"passed_time":0.2087411071,"remaining_time":1.337489316},
{"learn":[0.1046358493],"iteration":135,"passed_time":0.2102145432,"remaining_time":1.335480627},
{"learn":[0.1044839956],"iteration":136,"passed_time":0.2116817672,"remaining_time":1.333440621},
{"learn":[0.1041851068],"iteration":137,"passed_time":0.2132035376,"remaining_time":1.331749633},
{"learn":[0.1039702434],"iteration":138,"passed_time":0.2147269011,"remaining_time":1.330070949},
{"learn":[0.1036377904],"iteration":139,"passed_time":0.2162113988,"remaining_time":1.328155735},
{"learn":[0.103412485],"iteration":140,"passed_time":0.2177121783,"remaining_time":1.326345824},
{"learn":[0.1032186363],"iteration":141,"passed_time":0.2191975677,"remaining_time":1.324447275},
{"learn":[0.1029917959],"iteration":142,"passed_time":0.2207189974,"remaining_time":1.322770495},
{"learn":[0.1027890908],"iteration":143,"passed_time":0.2223164155,"remaining_time":1.321547581},
{"learn":[0.1025407734],"iteration":144,"passed_time":0.2237774574,"remaining_time":1.319515352},
{"learn":[0.102242403],"iteration":145,"passed_time":0.2252658026,"remaining_time":1.317650654},
{"learn":[0.1020453195],"iteration":146,"passed_time":0.2267175864,"remaining_time":1.31557892},
{"learn":[0.1018376852],"iteration":147,"passed_time":0.2281886278,"remaining_time":1.313626425},
{"learn":[0.1016805205],"iteration":148,"passed_time":0.2297360784,"remaining_time":1.312116797},
{"learn":[0.1014086321],"iteration":149,"passed_time":0.2312037232,"remaining_time":1.310154431},
{"learn":[0.1011767243],"iteration":150,"passed_time":0.23272366,"remaining_time":1.308492631},
{"learn":[0.1009491804],"iteration":151,"passed_time":0.2341977674,"remaining_time":1.306577018},
{"learn":[0.1007658144],"iteration":152,"passed_time":0.2357965081,"remaining_time":1.30535714},
{"learn":[0.1005178873],"iteration":153,"passed_time":0.2375198485,"remaining_time":1.30481683},
{"learn":[0.1003125377],"iteration":154,"passed_time":0.2391232082,"remaining_time":1.303607167},
{"learn":[0.1000458086],"iteration":155,"passed_time":0.2406589459,"remaining_time":1.302026604},
{"learn":[0.09976128967],"iteration":156,"passed_time":0.2421578216,"remaining_time":1.300248685},
{"learn":[0.09969579661],"iteration":157,"passed_time":0.2436453151,"remaining_time":1.298413641},
{"learn":[0.09963394974],"iteration":158,"passed_time":0.2451486896,"remaining_time":1.296666968},
{"learn":[0.09948205452],"iteration":159,"passed_time":0.2466249412,"remaining_time":1.294780941},
{"learn":[0.09927347364],"iteration":160,"passed_time":0.2481148394,"remaining_time":1.29297112},
{"learn":[0.09909133874],"iteration":161,"passed_time":0.2495787068,"remaining_time":1.291030595},
{"learn":[0.09889927893],"iteration":162,"passed_time":0.2510275249,"remaining_time":1.28901864},
{"learn":[0.0986595493],"iteration":163,"passed_time":0.2525933613,"remaining_time":1.287610061},
{"learn":[0.09847730321],"iteration":164,"passed_time":0.2540436422,"remaining_time":1.285614795},
{"learn":[0.09822372419],"iteration":165,"passed_time":0.2555044536,"remaining_time":1.283679002},
{"learn":[0.09814211705],"iteration":166,"passed_time":0.2569812563,"remaining_time":1.281828662},
{"learn":[0.09809969723],"iteration":167,"passed_time":0.2584396029,"remaining_time":1.279891367},
{"learn":[0.09801353202],"iteration":168,"passed_time":0.2598502064,"remaining_time":1.277724979},
{"learn":[0.09767897993],"iteration":169,"passed_time":0.261322881,"remaining_time":1.275870536},
{"learn":[0.09756204811],"iteration":170,"passed_time":0.2627413097,"remaining_time":1.273757577},
{"learn":[0.09750867288],"iteration":171,"passed_time":0.2641640769,"remaining_time":1.271673579},
{"learn":[0.09718934413],"iteration":172,"passed_time":0.2656348878,"remaining_time":1.269826891},
{"learn":[0.09690524168],"iteration":173,"passed_time":0.2671521895,"remaining_time":1.268205221},
{"learn":[0.09683081877],"iteration":174,"passed_time":0.2685988032,"remaining_time":1.266251501},
{"learn":[0.09663186772],"iteration":175,"passed_time":0.2700579314,"remaining_time":1.264362133},
{"learn":[0.09640956507],"iteration":176,"passed_time":0.2714899066,"remaining_time":1.262351373},
{"learn":[0.09628153271],"iteration":177,"passed_time":0.272984277,"remaining_time":1.260635257},
{"learn":[0.09604269594],"iteration":178,"passed_time":0.2744589655,"remaining_time":1.258831345},
{"learn":[0.09579713026],"iteration":179,"passed_time":0.2759546751,"remaining_time":1.257126853},
{"learn":[0.09550520901],"iteration":180,"passed_time":0.2774689208,"remaining_time":1.255508542},
{"learn":[0.09528537694],"iteration":181,"passed_time":0.2789484789,"remaining_time":1.253735471},
{"learn":[0.09497833952],"iteration":182,"passed_time":0.2804987249,"remaining_time":1.252281192},
{"learn":[0.09484560264],"iteration":183,"passed_time":0.2820749115,"remaining_time":1.250940912},
{"learn":[0.0947684831],"iteration":184,"passed_time":0.2827297397,"remaining_time":1.245539124},
{"learn":[0.09461853474],"iteration":185,"passed_time":0.2838347466,"remaining_time":1.242158515},
{"learn":[0.09456526002],"iteration":186,"passed_time":0.2853529401,"remaining_time":1.240598611},
{"learn":[0.09431688996],"iteration":187,"passed_time":0.2869020238,"remaining_time":1.239172571},
{"learn":[0.09425846098],"iteration":188,"passed_time":0.2883806,"remaining_time":1.23744268},
{"learn":[0.09403775556],"iteration":189,"passed_time":0.2899210769,"remaining_time":1.235979328},
{"learn":[0.0939434132],"iteration":190,"passed_time":0.291381708,"remaining_time":1.234176973},
{"learn":[0.09370538457],"iteration":191,"passed_time":0.2928781991,"remaining_time":1.232529088},
{"learn":[0.09343888264],"iteration":192,"passed_time":0.2943594304,"remaining_time":1.230818965},
{"learn":[0.09338867198],"iteration":193,"passed_time":0.2958681954,"remaining_time":1.229225595},
{"learn":[0.09310193452],"iteration":194,"passed_time":0.2974951912,"remaining_time":1.228121174},
{"learn":[0.09283542335],"iteration":195,"passed_time":0.2990349668,"remaining_time":1.226653639},
{"learn":[0.09277885311],"iteration":196,"passed_time":0.3005041947,"remaining_time":1.224897809},
{"learn":[0.09271973616],"iteration":197,"passed_time":0.3020072586,"remaining_time":1.223281926},
{"learn":[0.09255027722],"iteration":198,"passed_time":0.303500303,"remaining_time":1.221626848},
{"learn":[0.09236102988],"iteration":199,"passed_time":0.3050064629,"remaining_time":1.220025852},
{"learn":[0.09214683566],"iteration":200,"passed_time":0.3066015264,"remaining_time":1.218779202},
{"learn":[0.0918856415],"iteration":201,"passed_time":0.3081706894,"remaining_time":1.217426783},
{"learn":[0.09183437661],"iteration":202,"passed_time":0.3096979505,"remaining_time":1.215907717},
{"learn":[0.09178812081],"iteration":203,"passed_time":0.3112985047,"remaining_time":1.214674558},
{"learn":[0.09172001181],"iteration":204,"passed_time":0.3128373885,"remaining_time":1.213198653},
{"learn":[0.0916604626],"iteration":205,"passed_time":0.3142728505,"remaining_time":1.211323511},
{"learn":[0.091615991],"iteration":206,"passed_time":0.3157385816,"remaining_time":1.209568576},
{"learn":[0.09143226186],"iteration":207,"passed_time":0.3173094378,"remaining_time":1.208216705},
{"learn":[0.09119364435],"iteration":208,"passed_time":0.3188610765,"remaining_time":1.206790007},
{"learn":[0.09114611484],"iteration":209,"passed_time":0.3203438208,"remaining_time":1.205102945},
{"learn":[0.09093876974],"iteration":210,"passed_time":0.3218278676,"remaining_time":1.20342269},
{"learn":[0.09083577256],"iteration":211,"passed_time":0.3226488501,"remaining_time":1.199279688},
{"learn":[0.09054555337],"iteration":212,"passed_time":0.3241439785,"remaining_time":1.197658738},
{"learn":[0.09031651968],"iteration":213,"passed_time":0.3256354097,"remaining_time":1.196025383},
{"learn":[0.09005497193],"iteration":214,"passed_time":0.3272584579,"remaining_time":1.194873904},
{"learn":[0.09001742086],"iteration":215,"passed_time":0.3287751584,"remaining_time":1.193332056},
{"learn":[0.08980688916],"iteration":216,"passed_time":0.3302924601,"remaining_time":1.191792609},
{"learn":[0.08967451221],"iteration":217,"passed_time":0.3318542386,"remaining_time":1.190412911},
{"learn":[0.0894024869],"iteration":218,"passed_time":0.3333575731,"remaining_time":1.188823126},
{"learn":[0.08928983759],"iteration":219,"passed_time":0.3341678848,"remaining_time":1.184777046},
{"learn":[0.0890202895],"iteration":220,"passed_time":0.3356385254,"remaining_time":1.183087834},
{"learn":[0.08887517234],"iteration":221,"passed_time":0.3371145465,"remaining_time":1.181419447},
{"learn":[0.08874028448],"iteration":222,"passed_time":0.3385575632,"remaining_time":1.179637788},
{"learn":[0.08868396363],"iteration":223,"passed_time":0.3399919731,"remaining_time":1.177829335},
{"learn":[0.08849508013],"iteration":224,"passed_time":0.341475529,"remaining_time":1.176193489},
{"learn":[0.08845457334],"iteration":225,"passed_time":0.3430569057,"remaining_time":1.174894005},
{"learn":[0.08821440275],"iteration":226,"passed_time":0.3445719731,"remaining_time":1.173366234},
{"learn":[0.0879154857],"iteration":227,"passed_time":0.3461195339,"remaining_time":1.171948597},
{"learn":[0.08774959698],"iteration":228,"passed_time":0.3476066567,"remaining_time":1.170326342},
{"learn":[0.08770593713],"iteration":229,"passed_time":0.3490412169,"remaining_time":1.168529291},
{"learn":[0.08747320301],"iteration":230,"passed_time":0.3505521361,"remaining_time":1.166989579},
{"learn":[0.08743316363],"iteration":231,"passed_time":0.3520214842,"remaining_time":1.165312499},
{"learn":[0.08739220922],"iteration":232,"passed_time":0.3535597769,"remaining_time":1.163864158},
{"learn":[0.08722596541],"iteration":233,"passed_time":0.3550730507,"remaining_time":1.162333149},
{"learn":[0.08696707231],"iteration":234,"passed_time":0.3566268337,"remaining_time":1.160934161},
{"learn":[0.08676362625],"iteration":235,"passed_time":0.3582430484,"remaining_time":1.15973597},
{"learn":[0.08660311011],"iteration":236,"passed_time":0.3598092155,"remaining_time":1.158373128},
{"learn":[0.08641168942],"iteration":237,"passed_time":0.3612709187,"remaining_time":1.156674118},
{"learn":[0.08628969818],"iteration":238,"passed_time":0.3627475109,"remaining_time":1.155024501},
{"learn":[0.08623527266],"iteration":239,"passed_time":0.3641741357,"remaining_time":1.153218096},
{"learn":[0.08619984352],"iteration":240,"passed_time":0.3656068623,"remaining_time":1.15143406},
{"learn":[0.08592600004],"iteration":241,"passed_time":0.367102662,"remaining_time":1.149850487},
{"learn":[0.08565467959],"iteration":242,"passed_time":0.3686717548,"remaining_time":1.14849596},
{"learn":[0.08539379589],"iteration":243,"passed_time":0.3702183237,"remaining_time":1.147069888},
{"learn":[0.08509488168],"iteration":244,"passed_time":0.3718546742,"remaining_time":1.145919506},
{"learn":[0.08491710738],"iteration":245,"passed_time":0.3734550581,"remaining_time":1.144654934},
{"learn":[0.08477382231],"iteration":246,"passed_time":0.3749694241,"remaining_time":1.14312541},
{"learn":[0.08461196143],"iteration":247,"passed_time":0.3765041799,"remaining_time":1.141657836},
{"learn":[0.08439937539],"iteration":248,"passed_time":0.3779889581,"remaining_time":1.140038986},
{"learn":[0.08422528508],"iteration":249,"passed_time":0.3794711212,"remaining_time":1.138413364},
{"learn":[0.0841894873],"iteration":250,"passed_time":0.3809260311,"remaining_time":1.136707559},
{"learn":[0.08398410895],"iteration":251,"passed_time":0.3824461784,"remaining_time":1.135197387},
{"learn":[0.08384749263],"iteration":252,"passed_time":0.3838931929,"remaining_time":1.133471206},
{"learn":[0.08372964838],"iteration":253,"passed_time":0.3854380684,"remaining_time":1.132034642},
{"learn":[0.0836787418],"iteration":254,"passed_time":0.3871071299,"remaining_time":1.130960046},
{"learn":[0.0836360148],"iteration":255,"passed_time":0.3886054445,"remaining_time":1.129384573},
{"learn":[0.08341757359],"iteration":256,"passed_time":0.3902237333,"remaining_time":1.128156552},
{"learn":[0.08328522889],"iteration":257,"passed_time":0.3917328791,"remaining_time":1.126611614},
{"learn":[0.08316643318],"iteration":258,"passed_time":0.393207237,"remaining_time":1.124967423},
{"learn":[0.08313349567],"iteration":259,"passed_time":0.3946728578,"remaining_time":1.123299672},
{"learn":[0.08292189927],"iteration":260,"passed_time":0.3961423562,"remaining_time":1.121644449},
{"learn":[0.08288995936],"iteration":261,"passed_time":0.3976650385,"remaining_time":1.120140452},
{"learn":[0.08279653696],"iteration":262,"passed_time":0.3991362602,"remaining_time":1.118492106},
{"learn":[0.08254273743],"iteration":263,"passed_time":0.4006548745,"remaining_time":1.116977226},
{"learn":[0.08230027395],"iteration":264,"passed_time":0.4024108421,"remaining_time":1.116120637},
{"learn":[0.08218587639],"iteration":265,"passed_time":0.4039445758,"remaining_time":1.114644055},
{"learn":[0.08202209643],"iteration":266,"passed_time":0.4054573888,"remaining_time":1.11310961},
{"learn":[0.08184760385],"iteration":267,"passed_time":0.4069474774,"remaining_time":1.111513259},
{"learn":[0.0816187097],"iteration":268,"passed_time":0.4084624445,"remaining_time":1.109985305},
{"learn":[0.08158863109],"iteration":269,"passed_time":0.4099054612,"remaining_time":1.108262914},
{"learn":[0.08142988964],"iteration":270,"passed_time":0.4113963614,"remaining_time":1.106671393},
{"learn":[0.08122718186],"iteration":271,"passed_time":0.4129198752,"remaining_time":1.105167901},
{"learn":[0.08104628622],"iteration":272,"passed_time":0.4143830713,"remaining_time":1.103503637},
{"learn":[0.08094025517],"iteration":273,"passed_time":0.4159513125,"remaining_time":1.102119171},
{"learn":[0.08091024635],"iteration":274,"passed_time":0.4179958834,"remaining_time":1.101989147},
{"learn":[0.08087970076],"iteration":275,"passed_time":0.4195360898,"remaining_time":1.100522207},
{"learn":[0.08084983824],"iteration":276,"passed_time":0.4210487725,"remaining_time":1.098982897},
{"learn":[0.08064534298],"iteration":277,"passed_time":0.4225565256,"remaining_time":1.097430976},
{"learn":[0.08055750993],"iteration":278,"passed_time":0.4240166757,"remaining_time":1.095756356},
{"learn":[0.08047596354],"iteration":279,"passed_time":0.4255720517,"remaining_time":1.094328133},
{"learn":[0.0802610912],"iteration":280,"passed_time":0.4271421465,"remaining_time":1.092936667},
{"learn":[0.08005821702],"iteration":281,"passed_time":0.4286923023,"remaining_time":1.091493167},
{"learn":[0.08002991267],"iteration":282,"passed_time":0.4301521719,"remaining_time":1.089820167},
{"learn":[0.07988083564],"iteration":283,"passed_time":0.4318381329,"remaining_time":1.088718673},
{"learn":[0.07977663301],"iteration":284,"passed_time":0.433444555,"remaining_time":1.087413533},
{"learn":[0.07961779852],"iteration":285,"passed_time":0.4350650517,"remaining_time":1.086141423},
{"learn":[0.0794637395],"iteration":286,"passed_time":0.4365725242,"remaining_time":1.084586097},
{"learn":[0.07943720277],"iteration":287,"passed_time":0.4380342474,"remaining_time":1.082918001},
{"learn":[0.07940598364],"iteration":288,"passed_time":0.4394698096,"remaining_time":1.081186971},
{"learn":[0.0792649888],"iteration":289,"passed_time":0.4409303605,"remaining_time":1.079519158},
{"learn":[0.0792393864],"iteration":290,"passed_time":0.4423473263,"remaining_time":1.077746579},
{"learn":[0.07907049208],"iteration":291,"passed_time":0.4438408917,"remaining_time":1.076162162},
{"learn":[0.07904324174],"iteration":292,"passed_time":0.4452968637,"remaining_time":1.074487654},
{"learn":[0.07901870172],"iteration":293,"passed_time":0.4468960452,"remaining_time":1.07315853},
{"learn":[0.07890700953],"iteration":294,"passed_time":0.4486054018,"remaining_time":1.072090876},
{"learn":[0.07874455106],"iteration":295,"passed_time":0.4501850553,"remaining_time":1.070710402},
{"learn":[0.078719489],"iteration":296,"passed_time":0.4516246753,"remaining_time":1.068997127},
{"learn":[0.07851411155],"iteration":297,"passed_time":0.4530689345,"remaining_time":1.067296617},
{"learn":[0.07837394379],"iteration":298,"passed_time":0.4545560573,"remaining_time":1.065698315},
{"learn":[0.0782563265],"iteration":299,"passed_time":0.4560039835,"remaining_time":1.064009295},
{"learn":[0.07802672709],"iteration":300,"passed_time":0.4574667488,"remaining_time":1.062356337},
{"learn":[0.07790298823],"iteration":301,"passed_time":0.4588931831,"remaining_time":1.060620668},
{"learn":[0.07775366146],"iteration":302,"passed_time":0.4603587038,"remaining_time":1.058976952},
{"learn":[0.0776155592],"iteration":303,"passed_time":0.4619064314,"remaining_time":1.057522619},
{"learn":[0.07759214618],"iteration":304,"passed_time":0.4633548687,"remaining_time":1.055841422},
{"learn":[0.07756909884],"iteration":305,"passed_time":0.4648604775,"remaining_time":1.05429141},
{"learn":[0.07754759269],"iteration":306,"passed_time":0.4663339036,"remaining_time":1.05266904},
{"learn":[0.07735502533],"iteration":307,"passed_time":0.4678373783,"remaining_time":1.051115149},
{"learn":[0.07718692982],"iteration":308,"passed_time":0.4695074382,"remaining_time":1.049934109},
{"learn":[0.0771406259],"iteration":309,"passed_time":0.4711741315,"remaining_time":1.048742422},
{"learn":[0.07702454017],"iteration":310,"passed_time":0.472659561,"remaining_time":1.047146101},
{"learn":[0.07689578766],"iteration":311,"passed_time":0.4741477559,"remaining_time":1.04555659},
{"learn":[0.07681948958],"iteration":312,"passed_time":0.4755947103,"remaining_time":1.043877208},
{"learn":[0.07665646943],"iteration":313,"passed_time":0.4771994362,"remaining_time":1.042543991},
{"learn":[0.0765289986],"iteration":314,"passed_time":0.4786664898,"remaining_time":1.040909668},
{"learn":[0.07634824645],"iteration":315,"passed_time":0.4802197918,"remaining_time":1.039463094},
{"learn":[0.07621254732],"iteration":316,"passed_time":0.4817120947,"remaining_time":1.037884418},
{"learn":[0.07609254142],"iteration":317,"passed_time":0.4831882761,"remaining_time":1.036271712},
{"learn":[0.0759667494],"iteration":318,"passed_time":0.4846581653,"remaining_time":1.034646428},
{"learn":[0.07578575243],"iteration":319,"passed_time":0.4861543758,"remaining_time":1.033078049},
{"learn":[0.07565681896],"iteration":320,"passed_time":0.4876113698,"remaining_time":1.031427165},
{"learn":[0.07555029596],"iteration":321,"passed_time":0.4890576829,"remaining_time":1.029754997},
{"learn":[0.07538146596],"iteration":322,"passed_time":0.4905129736,"remaining_time":1.028103044},
{"learn":[0.07521708901],"iteration":323,"passed_time":0.4920938594,"remaining_time":1.026714349},
{"learn":[0.07499354508],"iteration":324,"passed_time":0.4935656122,"remaining_time":1.02509781},
{"learn":[0.07488965926],"iteration":325,"passed_time":0.4950517631,"remaining_time":1.023511927},
{"learn":[0.07472385405],"iteration":326,"passed_time":0.4965283353,"remaining_time":1.021906941},
{"learn":[0.07453707238],"iteration":327,"passed_time":0.4980053384,"remaining_time":1.02030362},
{"learn":[0.074394222],"iteration":328,"passed_time":0.4994823815,"remaining_time":1.018701149},
{"learn":[0.07422633478],"iteration":329,"passed_time":0.5009681416,"remaining_time":1.017117136},
{"learn":[0.07418745912],"iteration":330,"passed_time":0.5024321193,"remaining_time":1.015489691},
{"learn":[0.07415029651],"iteration":331,"passed_time":0.503845418,"remaining_time":1.013761263},
{"learn":[0.07402610765],"iteration":332,"passed_time":0.5055195658,"remaining_time":1.012557208},
{"learn":[0.07387483622],"iteration":333,"passed_time":0.5072433907,"remaining_time":1.011449396},
{"learn":[0.07365703526],"iteration":334,"passed_time":0.5088601665,"remaining_time":1.010125405},
{"learn":[0.07354947276],"iteration":335,"passed_time":0.5104512422,"remaining_time":1.008748883},
{"learn":[0.0735306838],"iteration":336,"passed_time":0.5119466212,"remaining_time":1.007182818},
{"learn":[0.07332495882],"iteration":337,"passed_time":0.5134668486,"remaining_time":1.00566584},
{"learn":[0.07322162335],"iteration":338,"passed_time":0.5149588609,"remaining_time":1.004093826},
{"learn":[0.07311953203],"iteration":339,"passed_time":0.5165300177,"remaining_time":1.002675917},
{"learn":[0.07298684281],"iteration":340,"passed_time":0.5180784302,"remaining_time":1.001213154},
{"learn":[0.07295077032],"iteration":341,"passed_time":0.5197180171,"remaining_time":0.9999253077},
{"learn":[0.07293316191],"iteration":342,"passed_time":0.5214212953,"remaining_time":0.9987574082},
{"learn":[0.0728138442],"iteration":343,"passed_time":0.5231356882,"remaining_time":0.9976075915},
{"learn":[0.07270094413],"iteration":344,"passed_time":0.5247878467,"remaining_time":0.9963363466},
{"learn":[0.07257263295],"iteration":345,"passed_time":0.5264236462,"remaining_time":0.9950319786},
{"learn":[0.07240495469],"iteration":346,"passed_time":0.5279859693,"remaining_time":0.9935874292},
{"learn":[0.07231096159],"iteration":347,"passed_time":0.529484324,"remaining_time":0.9920223542},
{"learn":[0.07229326523],"iteration":348,"passed_time":0.5309383622,"remaining_time":0.9903749966},
{"learn":[0.07214032204],"iteration":349,"passed_time":0.5324083015,"remaining_time":0.9887582742},
{"learn":[0.07200005689],"iteration":350,"passed_time":0.5338813368,"remaining_time":0.9871481127},
{"learn":[0.07176850902],"iteration":351,"passed_time":0.5356193092,"remaining_time":0.9860264556},
{"learn":[0.07161165286],"iteration":352,"passed_time":0.5372318368,"remaining_time":0.9846713836},
{"learn":[0.07137820289],"iteration":353,"passed_time":0.5387677348,"remaining_time":0.9831750189},
{"learn":[0.07126877367],"iteration":354,"passed_time":0.5402585648,"remaining_time":0.9815965474},
{"learn":[0.0711309984],"iteration":355,"passed_time":0.541793501,"remaining_time":0.9800983557},
{"learn":[0.07101822853],"iteration":356,"passed_time":0.543254082,"remaining_time":0.9784660356},
{"learn":[0.07093883348],"iteration":357,"passed_time":0.5446927802,"remaining_time":0.9767954327},
{"learn":[0.07092173468],"iteration":358,"passed_time":0.5461374502,"remaining_time":0.9751367843},
{"learn":[0.07083832601],"iteration":359,"passed_time":0.5476089825,"remaining_time":0.9735270801},
{"learn":[0.07067519498],"iteration":360,"passed_time":0.54910029,"remaining_time":0.9719531449},
{"learn":[0.07056813729],"iteration":361,"passed_time":0.5507780184,"remaining_time":0.9707082202},
{"learn":[0.07053088921],"iteration":362,"passed_time":0.5523017626,"remaining_time":0.9691906964},
{"learn":[0.07031900246],"iteration":363,"passed_time":0.5538260279,"remaining_time":0.9676740488},
{"learn":[0.07030310439],"iteration":364,"passed_time":0.5552654076,"remaining_time":0.9660096816},
{"learn":[0.07016243547],"iteration":365,"passed_time":0.5567209687,"remaining_time":0.9643745743},
{"learn":[0.07013316981],"iteration":366,"passed_time":0.5581414615,"remaining_time":0.9626799595},
{"learn":[0.0701177845],"iteration":367,"passed_time":0.5595878047,"remaining_time":0.9610312298},
{"learn":[0.06995714031],"iteration":368,"passed_time":0.5610785546,"remaining_time":0.9594595337},
{"learn":[0.06984690016],"iteration":369,"passed_time":0.5625440051,"remaining_time":0.9578451978},
{"learn":[0.06960111286],"iteration":370,"passed_time":0.5641149415,"remaining_time":0.9564105072},
{"learn":[0.06949987729],"iteration":371,"passed_time":0.5657347132,"remaining_time":0.9550575266},
{"learn":[0.06942470612],"iteration":372,"passed_time":0.5673215807,"remaining_time":0.9536478045},
{"learn":[0.0693688258],"iteration":373,"passed_time":0.5688657649,"remaining_time":0.952165692},
{"learn":[0.06919562452],"iteration":374,"passed_time":0.5704069332,"remaining_time":0.9506782219},
{"learn":[0.069120982],"iteration":375,"passed_time":0.5719441437,"remaining_time":0.9491838981},
{"learn":[0.06898700797],"iteration":376,"passed_time":0.573459672,"remaining_time":0.9476535163},
{"learn":[0.06884023988],"iteration":377,"passed_time":0.5749900492,"remaining_time":0.9461476471},
{"learn":[0.06873739624],"iteration":378,"passed_time":0.5764994856,"remaining_time":0.9446073365},
{"learn":[0.06863614961],"iteration":379,"passed_time":0.5780281094,"remaining_time":0.9430984942},
{"learn":[0.06861512689],"iteration":380,"passed_time":0.5798149572,"remaining_time":0.9420090775},
{"learn":[0.06857258455],"iteration":381,"passed_time":0.581562819,"remaining_time":0.9408529375},
{"learn":[0.0685590372],"iteration":382,"passed_time":0.5832304341,"remaining_time":0.939564433},
{"learn":[0.06850740273],"iteration":383,"passed_time":0.584700714,"remaining_time":0.9379573954},
{"learn":[0.06839788182],"iteration":384,"passed_time":0.5861636095,"remaining_time":0.9363392723},
{"learn":[0.06831286162],"iteration":385,"passed_time":0.5877114508,"remaining_time":0.9348570746},
{"learn":[0.06812668333],"iteration":386,"passed_time":0.5892021205,"remaining_time":0.9332839791},
{"learn":[0.06803733888],"iteration":387,"passed_time":0.590747467,"remaining_time":0.931797551},
{"learn":[0.06790843494],"iteration":388,"passed_time":0.5923583414,"remaining_time":0.9304137444},
{"learn":[0.0678618427],"iteration":389,"passed_time":0.5938058869,"remaining_time":0.9287733103},
{"learn":[0.0677533232],"iteration":390,"passed_time":0.5953419853,"remaining_time":0.9272717878},
{"learn":[0.06767599607],"iteration":391,"passed_time":0.5968477109,"remaining_time":0.9257229802},
{"learn":[0.06747581781],"iteration":392,"passed_time":0.5983945403,"remaining_time":0.9242378777},
{"learn":[0.06739139546],"iteration":393,"passed_time":0.5999465597,"remaining_time":0.9227604447},
{"learn":[0.06725696738],"iteration":394,"passed_time":0.601554809,"remaining_time":0.921368758},
{"learn":[0.06714095968],"iteration":395,"passed_time":0.6030975503,"remaining_time":0.9198760616},
{"learn":[0.06699796254],"iteration":396,"passed_time":0.6046644989,"remaining_time":0.9184198813},
{"learn":[0.0668195714],"iteration":397,"passed_time":0.6062034229,"remaining_time":0.9169207552},
{"learn":[0.06674825779],"iteration":398,"passed_time":0.6077448316,"remaining_time":0.9154251724},
{"learn":[0.06673399894],"iteration":399,"passed_time":0.6092961833,"remaining_time":0.9139442749},
{"learn":[0.06665092497],"iteration":400,"passed_time":0.6109672552,"remaining_time":0.9126418599},
{"learn":[0.06645948844],"iteration":401,"passed_time":0.6125529103,"remaining_time":0.9112105481},
{"learn":[0.06626868066],"iteration":402,"passed_time":0.614113256,"remaining_time":0.9097409773},
{"learn":[0.06619107747],"iteration":403,"passed_time":0.6155786464,"remaining_time":0.9081308744},
{"learn":[0.0660966004],"iteration":404,"passed_time":0.617068254,"remaining_time":0.9065570646},
{"learn":[0.06603380838],"iteration":405,"passed_time":0.6185742537,"remaining_time":0.9050076519},
{"learn":[0.06599201358],"iteration":406,"passed_time":0.6200683701,"remaining_time":0.9034411388},
{"learn":[0.06594881478],"iteration":407,"passed_time":0.6215711836,"remaining_time":0.9018875997},
{"learn":[0.06587273394],"iteration":408,"passed_time":0.6230889762,"remaining_time":0.9003559534},
{"learn":[0.06569185485],"iteration":409,"passed_time":0.6247061028,"remaining_time":0.8989673186},
{"learn":[0.06544208364],"iteration":410,"passed_time":0.6263084871,"remaining_time":0.897556445},
{"learn":[0.06524346074],"iteration":411,"passed_time":0.6278475713,"remaining_time":0.8960543008},
{"learn":[0.06512579518],"iteration":412,"passed_time":0.6293496032,"remaining_time":0.894499315},
{"learn":[0.06510002943],"iteration":413,"passed_time":0.6308058457,"remaining_time":0.892879772},
{"learn":[0.0649578251],"iteration":414,"passed_time":0.6322649138,"remaining_time":0.8912649989},
{"learn":[0.06484478451],"iteration":415,"passed_time":0.6337220781,"remaining_time":0.8896483019},
{"learn":[0.06475005925],"iteration":416,"passed_time":0.6351613876,"remaining_time":0.8880074075},
{"learn":[0.06473472514],"iteration":417,"passed_time":0.6365807681,"remaining_time":0.8863397298},
{"learn":[0.06455501155],"iteration":418,"passed_time":0.638107378,"remaining_time":0.8848219251},
{"learn":[0.06440409013],"iteration":419,"passed_time":0.6397539821,"remaining_time":0.8834697848},
{"learn":[0.06435170419],"iteration":420,"passed_time":0.6414810202,"remaining_time":0.8822268663},
{"learn":[0.06426906989],"iteration":421,"passed_time":0.6431929318,"remaining_time":0.880960935},
{"learn":[0.06405610432],"iteration":422,"passed_time":0.644895445,"remaining_time":0.8796800751},
{"learn":[0.06394825095],"iteration":423,"passed_time":0.6465695528,"remaining_time":0.8783586378},
{"learn":[0.06393542267],"iteration":424,"passed_time":0.6482121892,"remaining_time":0.8769929618},
{"learn":[0.06381774638],"iteration":425,"passed_time":0.6498856156,"remaining_time":0.8756674727},
{"learn":[0.06380551372],"iteration":426,"passed_time":0.651521098,"remaining_time":0.874289436},
{"learn":[0.06373588798],"iteration":427,"passed_time":0.6532142129,"remaining_time":0.8729872191},
{"learn":[0.06370936301],"iteration":428,"passed_time":0.6548780105,"remaining_time":0.8716441586},
{"learn":[0.06361747583],"iteration":429,"passed_time":0.656574983,"remaining_time":0.8703435821},
{"learn":[0.06342309271],"iteration":430,"passed_time":0.658263048,"remaining_time":0.8690294067},
{"learn":[0.06327795722],"iteration":431,"passed_time":0.6599516741,"remaining_time":0.8677142382},
{"learn":[0.06318207813],"iteration":432,"passed_time":0.6615922565,"remaining_time":0.8663344328},
{"learn":[0.0630892576],"iteration":433,"passed_time":0.663233961,"remaining_time":0.8649548892},
{"learn":[0.06295431195],"iteration":434,"passed_time":0.6649339192,"remaining_time":0.8636498032},
{"learn":[0.06285957141],"iteration":435,"passed_time":0.6666614613,"remaining_time":0.8623785876},
{"learn":[0.06269657078],"iteration":436,"passed_time":0.6683371221,"remaining_time":0.8610384434},
{"learn":[0.06255355318],"iteration":437,"passed_time":0.6700242253,"remaining_time":0.8597114489},
{"learn":[0.06242042381],"iteration":438,"passed_time":0.6717175506,"remaining_time":0.8583907651},
{"learn":[0.06229335647],"iteration":439,"passed_time":0.6734525372,"remaining_time":0.857121411},
{"learn":[0.0621844416],"iteration":440,"passed_time":0.6750885206,"remaining_time":0.8557244513},
{"learn":[0.06200431355],"iteration":441,"passed_time":0.67679934,"remaining_time":0.8544208863},
{"learn":[0.06195529724],"iteration":442,"passed_time":0.678434582,"remaining_time":0.8530204563},
{"learn":[0.0619388371],"iteration":443,"passed_time":0.680060165,"remaining_time":0.8516068733},
{"learn":[0.0618287815],"iteration":444,"passed_time":0.6818086079,"remaining_time":0.8503455672},
{"learn":[0.06171745613],"iteration":445,"passed_time":0.6835358459,"remaining_time":0.8490557368},
{"learn":[0.0615579622],"iteration":446,"passed_time":0.6851345465,"remaining_time":0.8476049311},
{"learn":[0.06141199933],"iteration":447,"passed_time":0.6866784401,"remaining_time":0.8460859351},
{"learn":[0.06123803072],"iteration":448,"passed_time":0.6882418318,"remaining_time":0.8445907557},
{"learn":[0.06113874983],"iteration":449,"passed_time":0.6898057946,"remaining_time":0.8430959711},
{"learn":[0.06112684479],"iteration":450,"passed_time":0.6913180665,"remaining_time":0.8415379567},
{"learn":[0.06103081351],"iteration":451,"passed_time":0.6929173281,"remaining_time":0.8400856102},
{"learn":[0.06093539243],"iteration":452,"passed_time":0.6944560617,"remaining_time":0.838559527},
{"learn":[0.06084636586],"iteration":453,"passed_time":0.6960083818,"remaining_time":0.8370497278},
{"learn":[0.06068757757],"iteration":454,"passed_time":0.6975859511,"remaining_time":0.8355699854},
{"learn":[0.06065452332],"iteration":455,"passed_time":0.6993477666,"remaining_time":0.8343096163},
{"learn":[0.06055986825],"iteration":456,"passed_time":0.7008903176,"remaining_time":0.8327865261},
{"learn":[0.06046278522],"iteration":457,"passed_time":0.7023944536,"remaining_time":0.8312178905},
{"learn":[0.0604079771],"iteration":458,"passed_time":0.7038395343,"remaining_time":0.8295799304},
{"learn":[0.06029027108],"iteration":459,"passed_time":0.705315315,"remaining_time":0.827978848},
{"learn":[0.06022046192],"iteration":460,"passed_time":0.7067933901,"remaining_time":0.8263809919},
{"learn":[0.06016048847],"iteration":461,"passed_time":0.7082972456,"remaining_time":0.8248136756},
{"learn":[0.06003812493],"iteration":462,"passed_time":0.7098004097,"remaining_time":0.8232458315},
{"learn":[0.05989888431],"iteration":463,"passed_time":0.7113511502,"remaining_time":0.8217332252},
{"learn":[0.05984262414],"iteration":464,"passed_time":0.7128874991,"remaining_time":0.8202038968},
{"learn":[0.05972746398],"iteration":465,"passed_time":0.714554002,"remaining_time":0.8188236847},
{"learn":[0.05958474],"iteration":466,"passed_time":0.7160518056,"remaining_time":0.8172497054},
{"learn":[0.05955314615],"iteration":467,"passed_time":0.7174867967,"remaining_time":0.8156046492},
{"learn":[0.05946956777],"iteration":468,"passed_time":0.7190020544,"remaining_time":0.8140513665},
{"learn":[0.05932517218],"iteration":469,"passed_time":0.7205469199,"remaining_time":0.8125316331},
{"learn":[0.05925097842],"iteration":470,"passed_time":0.7220532803,"remaining_time":0.8109685462},
{"learn":[0.05917752],"iteration":471,"passed_time":0.7235279187,"remaining_time":0.8093702141},
{"learn":[0.05911367809],"iteration":472,"passed_time":0.7249987798,"remaining_time":0.8077681965},
{"learn":[0.05896048423],"iteration":473,"passed_time":0.7264790191,"remaining_time":0.8061771394},
{"learn":[0.05883397832],"iteration":474,"passed_time":0.7280234002,"remaining_time":0.8046574423},
{"learn":[0.05879887716],"iteration":475,"passed_time":0.7296659098,"remaining_time":0.8032456654},
{"learn":[0.0586668178],"iteration":476,"passed_time":0.7312643499,"remaining_time":0.8017846016},
{"learn":[0.05851808352],"iteration":477,"passed_time":0.7327670531,"remaining_time":0.8002184136},
{"learn":[0.05846898785],"iteration":478,"passed_time":0.7342461502,"remaining_time":0.7986268147},
{"learn":[0.05835046018],"iteration":479,"passed_time":0.7357398959,"remaining_time":0.7970515539},
{"learn":[0.05834000159],"iteration":480,"passed_time":0.7371872511,"remaining_time":0.7954265766},
{"learn":[0.05821853596],"iteration":481,"passed_time":0.7386294963,"remaining_time":0.7937968446},
{"learn":[0.0580643399],"iteration":482,"passed_time":0.7401347144,"remaining_time":0.7922352948},
{"learn":[0.0580538505],"iteration":483,"passed_time":0.7416381456,"remaining_time":0.7906720726},
{"learn":[0.05804370408],"iteration":484,"passed_time":0.7430710425,"remaining_time":0.7890341998},
{"learn":[0.05796477078],"iteration":485,"passed_time":0.7447909798,"remaining_time":0.7877007482},
{"learn":[0.05795246958],"iteration":486,"passed_time":0.7463078141,"remaining_time":0.7861517631},
{"learn":[0.05783387858],"iteration":487,"passed_time":0.7478684003,"remaining_time":0.7846488134},
{"learn":[0.05771185689],"iteration":488,"passed_time":0.7493130201,"remaining_time":0.7830244443},
{"learn":[0.05759996497],"iteration":489,"passed_time":0.7508216849,"remaining_time":0.781467468},
{"learn":[0.05747036038],"iteration":490,"passed_time":0.7523454393,"remaining_time":0.7799263311},
{"learn":[0.05741320449],"iteration":491,"passed_time":0.7539040015,"remaining_time":0.7784212048},
{"learn":[0.05738735237],"iteration":492,"passed_time":0.755363831,"remaining_time":0.7768143252},
{"learn":[0.05727154819],"iteration":493,"passed_time":0.7569495062,"remaining_time":0.7753369436},
{"learn":[0.05717541578],"iteration":494,"passed_time":0.7584793223,"remaining_time":0.7738021369},
{"learn":[0.05712926892],"iteration":495,"passed_time":0.759939733,"remaining_time":0.7721968255},
{"learn":[0.05702836692],"iteration":496,"passed_time":0.7614480972,"remaining_time":0.7706406296},
{"learn":[0.05689644972],"iteration":497,"passed_time":0.7629401096,"remaining_time":0.7690681426},
{"learn":[0.05683253278],"iteration":498,"passed_time":0.7643466351,"remaining_time":0.7674101486},
{"learn":[0.05674900403],"iteration":499,"passed_time":0.7658127068,"remaining_time":0.7658127068},
{"learn":[0.05662949115],"iteration":500,"passed_time":0.7673182555,"remaining_time":0.7642551088},
{"learn":[0.05654515981],"iteration":501,"passed_time":0.7687908901,"remaining_time":0.7626650662},
{"learn":[0.05650338622],"iteration":502,"passed_time":0.7702622321,"remaining_time":0.7610742134},
{"learn":[0.05640938194],"iteration":503,"passed_time":0.7717721694,"remaining_time":0.7595218175},
{"learn":[0.05631674651],"iteration":504,"passed_time":0.7733376351,"remaining_time":0.7580240186},
{"learn":[0.05617072473],"iteration":505,"passed_time":0.774932879,"remaining_time":0.7565550241},
{"learn":[0.05613177668],"iteration":506,"passed_time":0.7766963111,"remaining_time":0.7552490757},
{"learn":[0.05597770446],"iteration":507,"passed_time":0.7783491474,"remaining_time":0.7538342136},
{"learn":[0.05587592996],"iteration":508,"passed_time":0.7799337204,"remaining_time":0.7523525672},
{"learn":[0.0557575245],"iteration":509,"passed_time":0.7815628704,"remaining_time":0.7509133461},
{"learn":[0.0556310984],"iteration":510,"passed_time":0.7830969449,"remaining_time":0.7493823993},
{"learn":[0.055508054],"iteration":511,"passed_time":0.7845846789,"remaining_time":0.747807272},
{"learn":[0.05549470187],"iteration":512,"passed_time":0.786089396,"remaining_time":0.7462486079},
{"learn":[0.05537828831],"iteration":513,"passed_time":0.7875910972,"remaining_time":0.7446873021},
{"learn":[0.05527789722],"iteration":514,"passed_time":0.789152495,"remaining_time":0.7431824468},
{"learn":[0.05521164706],"iteration":515,"passed_time":0.7906136171,"remaining_time":0.7415833152},
{"learn":[0.05510115366],"iteration":516,"passed_time":0.7921024833,"remaining_time":0.7400106372},
{"learn":[0.05497689713],"iteration":517,"passed_time":0.7935476041,"remaining_time":0.7383975776},
{"learn":[0.05488556997],"iteration":518,"passed_time":0.7950154994,"remaining_time":0.736806272},
{"learn":[0.05474032163],"iteration":519,"passed_time":0.7964900576,"remaining_time":0.7352215917},
{"learn":[0.05461883578],"iteration":520,"passed_time":0.797963654,"remaining_time":0.7336364497},
{"learn":[0.05445563723],"iteration":521,"passed_time":0.7994810459,"remaining_time":0.732091839},
{"learn":[0.05435993676],"iteration":522,"passed_time":0.8009415568,"remaining_time":0.7304954543},
{"learn":[0.05434093253],"iteration":523,"passed_time":0.8023811869,"remaining_time":0.7288806201},
{"learn":[0.05419527107],"iteration":524,"passed_time":0.8038793412,"remaining_time":0.7273194039},
{"learn":[0.05408043988],"iteration":525,"passed_time":0.8053399422,"remaining_time":0.7257245867},
{"learn":[0.05399252078],"iteration":526,"passed_time":0.8068329465,"remaining_time":0.7241593619},
{"learn":[0.05391684408],"iteration":527,"passed_time":0.8083032765,"remaining_time":0.7225741411},
{"learn":[0.05387275487],"iteration":528,"passed_time":0.8097810811,"remaining_time":0.7209960099},
{"learn":[0.05374386055],"iteration":529,"passed_time":0.8112657391,"remaining_time":0.7194243347},
{"learn":[0.05367654262],"iteration":530,"passed_time":0.8127668693,"remaining_time":0.7178675361},
{"learn":[0.05361269762],"iteration":531,"passed_time":0.8143024667,"remaining_time":0.7163412677},
{"learn":[0.05353748472],"iteration":532,"passed_time":0.8158579494,"remaining_time":0.7148323872},
{"learn":[0.05345940977],"iteration":533,"passed_time":0.8174659682,"remaining_time":0.7133691782},
{"learn":[0.05338050785],"iteration":534,"passed_time":0.8191160691,"remaining_time":0.711942004},
{"learn":[0.05329263734],"iteration":535,"passed_time":0.8206815148,"remaining_time":0.7104407143},
{"learn":[0.05318206556],"iteration":536,"passed_time":0.8221909311,"remaining_time":0.7088908773},
{"learn":[0.05306139145],"iteration":537,"passed_time":0.8237546269,"remaining_time":0.7073878023},
{"learn":[0.05300637874],"iteration":538,"passed_time":0.8252677469,"remaining_time":0.7058412455},
{"learn":[0.05296452823],"iteration":539,"passed_time":0.8267453812,"remaining_time":0.704264584},
{"learn":[0.05286693032],"iteration":540,"passed_time":0.8282973641,"remaining_time":0.7027513681},
{"learn":[0.05277626738],"iteration":541,"passed_time":0.8298154373,"remaining_time":0.7012093548},
{"learn":[0.05276629555],"iteration":542,"passed_time":0.8312831823,"remaining_time":0.6996250724},
{"learn":[0.05269180515],"iteration":543,"passed_time":0.8328425927,"remaining_time":0.6981180557},
{"learn":[0.05255318154],"iteration":544,"passed_time":0.8344767425,"remaining_time":0.6966732437},
{"learn":[0.05246536951],"iteration":545,"passed_time":0.8360086427,"remaining_time":0.6951427176},
{"learn":[0.05239747145],"iteration":546,"passed_time":0.837465286,"remaining_time":0.6935498621},
{"learn":[0.05238906567],"iteration":547,"passed_time":0.8389059682,"remaining_time":0.6919443387},
{"learn":[0.05233920291],"iteration":548,"passed_time":0.8403588341,"remaining_time":0.6903494247},
{"learn":[0.0522915725],"iteration":549,"passed_time":0.8418405764,"remaining_time":0.6887786534},
{"learn":[0.0521538184],"iteration":550,"passed_time":0.8433284206,"remaining_time":0.6872131776},
{"learn":[0.05209517892],"iteration":551,"passed_time":0.8448108743,"remaining_time":0.6856436081},
{"learn":[0.05197448284],"iteration":552,"passed_time":0.846285653,"remaining_time":0.6840681499},
{"learn":[0.05190361463],"iteration":553,"passed_time":0.8479379382,"remaining_time":0.6826359574},
{"learn":[0.05172739658],"iteration":554,"passed_time":0.8494845972,"remaining_time":0.6811182806},
{"learn":[0.05165562955],"iteration":555,"passed_time":0.8509190672,"remaining_time":0.6795109098},
{"learn":[0.05153911038],"iteration":556,"passed_time":0.852412352,"remaining_time":0.6779509371},
{"learn":[0.05140387139],"iteration":557,"passed_time":0.8539339055,"remaining_time":0.6764135954},
{"learn":[0.05132434373],"iteration":558,"passed_time":0.8555059541,"remaining_time":0.6749161463},
{"learn":[0.05123715317],"iteration":559,"passed_time":0.857010551,"remaining_time":0.6733654329},
{"learn":[0.05110847858],"iteration":560,"passed_time":0.8585447357,"remaining_time":0.6718380374},
{"learn":[0.05101504901],"iteration":561,"passed_time":0.8599868807,"remaining_time":0.6702388857},
{"learn":[0.05092149782],"iteration":562,"passed_time":0.8614489346,"remaining_time":0.6686557449},
{"learn":[0.05080360127],"iteration":563,"passed_time":0.8635917372,"remaining_time":0.6675992862},
{"learn":[0.05070625057],"iteration":564,"passed_time":0.8652531703,"remaining_time":0.66616837},
{"learn":[0.05056381298],"iteration":565,"passed_time":0.8668870495,"remaining_time":0.6647155115},
{"learn":[0.05048761807],"iteration":566,"passed_time":0.868432426,"remaining_time":0.6631944276},
{"learn":[0.05041399582],"iteration":567,"passed_time":0.8699820674,"remaining_time":0.6616765019},
{"learn":[0.05032963588],"iteration":568,"passed_time":0.8715063963,"remaining_time":0.6601392914},
{"learn":[0.05021927258],"iteration":569,"passed_time":0.8730391682,"remaining_time":0.6586084953},
{"learn":[0.05011859091],"iteration":570,"passed_time":0.8746588097,"remaining_time":0.6571429586},
{"learn":[0.05006646618],"iteration":571,"passed_time":0.876623154,"remaining_time":0.6559348075},
{"learn":[0.04997508956],"iteration":572,"passed_time":0.8825714989,"remaining_time":0.6576928971},
{"learn":[0.04990931348],"iteration":573,"passed_time":0.8846448896,"remaining_time":0.6565482978},
{"learn":[0.04984532045],"iteration":574,"passed_time":0.8864094739,"remaining_time":0.6551722199},
{"learn":[0.04975761497],"iteration":575,"passed_time":0.8883258045,"remaining_time":0.653906495},
{"learn":[0.04962104977],"iteration":576,"passed_time":0.890190344,"remaining_time":0.6526005468},
{"learn":[0.04952141358],"iteration":577,"passed_time":0.8919191486,"remaining_time":0.6511935652},
{"learn":[0.04942552614],"iteration":578,"passed_time":0.8938847714,"remaining_time":0.6499576663},
{"learn":[0.04930674632],"iteration":579,"passed_time":0.8955412848,"remaining_time":0.6484954132},
{"learn":[0.04919143971],"iteration":580,"passed_time":0.8972108037,"remaining_time":0.6470418705},
{"learn":[0.04918063267],"iteration":581,"passed_time":0.8988291927,"remaining_time":0.6455508635},
{"learn":[0.04917225536],"iteration":582,"passed_time":0.9004146474,"remaining_time":0.6440358627},
{"learn":[0.04909626376],"iteration":583,"passed_time":0.9020211933,"remaining_time":0.6425356446},
{"learn":[0.04899337654],"iteration":584,"passed_time":0.9036827266,"remaining_time":0.641074071},
{"learn":[0.04889949786],"iteration":585,"passed_time":0.9053188703,"remaining_time":0.6395938776},
{"learn":[0.04888432126],"iteration":586,"passed_time":0.9070615469,"remaining_time":0.6381881071},
{"learn":[0.04876394997],"iteration":587,"passed_time":0.9088034971,"remaining_time":0.6367806816},
{"learn":[0.0486553227],"iteration":588,"passed_time":0.910506842,"remaining_time":0.6353451817},
{"learn":[0.04858605825],"iteration":589,"passed_time":0.9121954781,"remaining_time":0.6338985526},
{"learn":[0.0485150453],"iteration":590,"passed_time":0.9138546467,"remaining_time":0.6324307115},
{"learn":[0.04842279127],"iteration":591,"passed_time":0.9156213653,"remaining_time":0.6310363464},
{"learn":[0.04835971915],"iteration":592,"passed_time":0.9172860747,"remaining_time":0.6295707123},
{"learn":[0.04828635455],"iteration":593,"passed_time":0.9190148292,"remaining_time":0.6281481829},
{"learn":[0.04819216591],"iteration":594,"passed_time":0.9207025035,"remaining_time":0.626696662},
{"learn":[0.04808499938],"iteration":595,"passed_time":0.9225546888,"remaining_time":0.6253558629},
{"learn":[0.04801577977],"iteration":596,"passed_time":0.9243485905,"remaining_time":0.6239740066},
{"learn":[0.04794057372],"iteration":597,"passed_time":0.9262629161,"remaining_time":0.6226717262},
{"learn":[0.04787827703],"iteration":598,"passed_time":0.9280877281,"remaining_time":0.6213074774},
{"learn":[0.04779648921],"iteration":599,"passed_time":0.9298306001,"remaining_time":0.6198870667},
{"learn":[0.04770974603],"iteration":600,"passed_time":0.9315009305,"remaining_time":0.6184174231},
{"learn":[0.04761621215],"iteration":601,"passed_time":0.9332302461,"remaining_time":0.6169861095},
{"learn":[0.04756598688],"iteration":602,"passed_time":0.9349240723,"remaining_time":0.6155304423},
{"learn":[0.04754709132],"iteration":603,"passed_time":0.9366552415,"remaining_time":0.6140984696},
{"learn":[0.04751128488],"iteration":604,"passed_time":0.9382827383,"remaining_time":0.6125978209},
{"learn":[0.04744573055],"iteration":605,"passed_time":0.9399749214,"remaining_time":0.6111388103},
{"learn":[0.0473762263],"iteration":606,"passed_time":0.9416891775,"remaining_time":0.6096933225},
{"learn":[0.04725044891],"iteration":607,"passed_time":0.9433941656,"remaining_time":0.6082409752},
{"learn":[0.04719817818],"iteration":608,"passed_time":0.9450858677,"remaining_time":0.6067792681},
{"learn":[0.04710152416],"iteration":609,"passed_time":0.9468046928,"remaining_time":0.6053341479},
{"learn":[0.04709406362],"iteration":610,"passed_time":0.9484417082,"remaining_time":0.6038360466},
{"learn":[0.04707564998],"iteration":611,"passed_time":0.950077912,"remaining_time":0.6023369769},
{"learn":[0.04701876881],"iteration":612,"passed_time":0.9517902644,"remaining_time":0.600885534},
{"learn":[0.04698838282],"iteration":613,"passed_time":0.9534548035,"remaining_time":0.5994031827},
{"learn":[0.04690086538],"iteration":614,"passed_time":0.9551368869,"remaining_time":0.5979312219},
{"learn":[0.0468935866],"iteration":615,"passed_time":0.9568914918,"remaining_time":0.5965037871},
{"learn":[0.04679625065],"iteration":616,"passed_time":0.9586196952,"remaining_time":0.5950589032},
{"learn":[0.04675033267],"iteration":617,"passed_time":0.9602941937,"remaining_time":0.5935799062},
{"learn":[0.04664763896],"iteration":618,"passed_time":0.9620015063,"remaining_time":0.5921204748},
{"learn":[0.04658103282],"iteration":619,"passed_time":0.963684792,"remaining_time":0.5906455177},
{"learn":[0.04650726872],"iteration":620,"passed_time":0.9653611242,"remaining_time":0.5891656458},
{"learn":[0.04642864819],"iteration":621,"passed_time":0.9671737488,"remaining_time":0.5877679695},
{"learn":[0.04637367788],"iteration":622,"passed_time":0.9692597165,"remaining_time":0.586534371},
{"learn":[0.04626657097],"iteration":623,"passed_time":0.9709306847,"remaining_time":0.5850479767},
{"learn":[0.04618461535],"iteration":624,"passed_time":0.9725392345,"remaining_time":0.5835235407},
{"learn":[0.04613101715],"iteration":625,"passed_time":0.9741384661,"remaining_time":0.5819932689},
{"learn":[0.04607019695],"iteration":626,"passed_time":0.975709613,"remaining_time":0.5804460696},
{"learn":[0.04600226773],"iteration":627,"passed_time":0.9772929871,"remaining_time":0.578906037},
{"learn":[0.04595437079],"iteration":628,"passed_time":0.978861068,"remaining_time":0.5773568461},
{"learn":[0.0458495194],"iteration":629,"passed_time":0.98051174,"remaining_time":0.5758561013},
{"learn":[0.04571679467],"iteration":630,"passed_time":0.9821605684,"remaining_time":0.5743538031},
{"learn":[0.04565262982],"iteration":631,"passed_time":0.9837706813,"remaining_time":0.572828498},
{"learn":[0.04552286466],"iteration":632,"passed_time":0.985307441,"remaining_time":0.5712603963},
{"learn":[0.04548273473],"iteration":633,"passed_time":0.9867568101,"remaining_time":0.569641944},
{"learn":[0.04542718507],"iteration":634,"passed_time":0.9882399151,"remaining_time":0.5680434157},
{"learn":[0.04534526299],"iteration":635,"passed_time":0.9896980413,"remaining_time":0.5664309544},
{"learn":[0.04528380681],"iteration":636,"passed_time":0.9911702449,"remaining_time":0.5648269999},
{"learn":[0.04520539555],"iteration":637,"passed_time":0.9926597524,"remaining_time":0.5632332764},
{"learn":[0.04511588415],"iteration":638,"passed_time":0.9941089311,"remaining_time":0.5616170957},
{"learn":[0.0450620949],"iteration":639,"passed_time":0.9957924072,"remaining_time":0.5601332291},
{"learn":[0.04498541278],"iteration":640,"passed_time":0.997398372,"remaining_time":0.5586053285},
{"learn":[0.04487381642],"iteration":641,"passed_time":0.998890735,"remaining_time":0.5570138367},
{"learn":[0.04480709865],"iteration":642,"passed_time":1.000448045,"remaining_time":0.5554587123},
{"learn":[0.04471588177],"iteration":643,"passed_time":1.001919677,"remaining_time":0.5538562192},
{"learn":[0.04464192012],"iteration":644,"passed_time":1.003453969,"remaining_time":0.5522886185},
{"learn":[0.04460637775],"iteration":645,"passed_time":1.004939679,"remaining_time":0.5506944989},
{"learn":[0.04453936281],"iteration":646,"passed_time":1.006465136,"remaining_time":0.5491224005},
{"learn":[0.04444647911],"iteration":647,"passed_time":1.007923403,"remaining_time":0.5475139472},
{"learn":[0.04438693341],"iteration":648,"passed_time":1.009405596,"remaining_time":0.5459188971},
{"learn":[0.04433799717],"iteration":649,"passed_time":1.01094431,"remaining_time":0.5443546282},
{"learn":[0.04426162829],"iteration":650,"passed_time":1.012493664,"remaining_time":0.5427961424},
{"learn":[0.04419906967],"iteration":651,"passed_time":1.014075822,"remaining_time":0.5412551934},
{"learn":[0.04411625865],"iteration":652,"passed_time":1.015626659,"remaining_time":0.5396974744},
{"learn":[0.04401681202],"iteration":653,"passed_time":1.017176434,"remaining_time":0.5381392145},
{"learn":[0.0439533108],"iteration":654,"passed_time":1.018730728,"remaining_time":0.5365833607},
{"learn":[0.04390415757],"iteration":655,"passed_time":1.020286876,"remaining_time":0.5350284837},
{"learn":[0.04384428019],"iteration":656,"passed_time":1.02179515,"remaining_time":0.5334486095},
{"learn":[0.04379499057],"iteration":657,"passed_time":1.023323483,"remaining_time":0.5318793788},
{"learn":[0.04378779664],"iteration":658,"passed_time":1.024858239,"remaining_time":0.5303135956},
{"learn":[0.04370749013],"iteration":659,"passed_time":1.026575254,"remaining_time":0.5288417975},
{"learn":[0.04364765286],"iteration":660,"passed_time":1.028160218,"remaining_time":0.5273015338},
{"learn":[0.04360654516],"iteration":661,"passed_time":1.029634686,"remaining_time":0.5257047188},
{"learn":[0.04353725396],"iteration":662,"passed_time":1.03112758,"remaining_time":0.5241176387},
{"learn":[0.04341826133],"iteration":663,"passed_time":1.032591247,"remaining_time":0.5225160527},
{"learn":[0.04336436523],"iteration":664,"passed_time":1.034081215,"remaining_time":0.520928131},
{"learn":[0.04329625473],"iteration":665,"passed_time":1.035548409,"remaining_time":0.5193290821},
{"learn":[0.04320168737],"iteration":666,"passed_time":1.03699355,"remaining_time":0.5177194185},
{"learn":[0.04312036595],"iteration":667,"passed_time":1.038505682,"remaining_time":0.5161435424},
{"learn":[0.04306296373],"iteration":668,"passed_time":1.040084133,"remaining_time":0.5146006696},
{"learn":[0.04300300848],"iteration":669,"passed_time":1.041596996,"remaining_time":0.513025386},
{"learn":[0.04290571142],"iteration":670,"passed_time":1.043062867,"remaining_time":0.5114272478},
{"learn":[0.04286334414],"iteration":671,"passed_time":1.044563095,"remaining_time":0.5098462728},
{"learn":[0.04278837333],"iteration":672,"passed_time":1.046067191,"remaining_time":0.5082674169},
{"learn":[0.04268952972],"iteration":673,"passed_time":1.047535117,"remaining_time":0.5066712879},
{"learn":[0.0425978741],"iteration":674,"passed_time":1.048983193,"remaining_time":0.505065982},
{"learn":[0.04252352733],"iteration":675,"passed_time":1.050445438,"remaining_time":0.5034679316},
{"learn":[0.04243282247],"iteration":676,"passed_time":1.05197336,"remaining_time":0.5019016178},
{"learn":[0.04234205839],"iteration":677,"passed_time":1.053437648,"remaining_time":0.5003051958},
{"learn":[0.04226419174],"iteration":678,"passed_time":1.055101736,"remaining_time":0.4988036191},
{"learn":[0.0422212308],"iteration":679,"passed_time":1.056634979,"remaining_time":0.4972399902},
{"learn":[0.04217919077],"iteration":680,"passed_time":1.058154776,"remaining_time":0.495670152},
{"learn":[0.04215656882],"iteration":681,"passed_time":1.059713899,"remaining_time":0.4941187976},
{"learn":[0.04209683411],"iteration":682,"passed_time":1.061306084,"remaining_time":0.492582765},
{"learn":[0.04201386646],"iteration":683,"passed_time":1.062921898,"remaining_time":0.4910574848},
{"learn":[0.04192392984],"iteration":684,"passed_time":1.064512001,"remaining_time":0.4895201174},
{"learn":[0.04186245676],"iteration":685,"passed_time":1.06603272,"remaining_time":0.4879508367},
{"learn":[0.04179684042],"iteration":686,"passed_time":1.067605309,"remaining_time":0.4864053302},
{"learn":[0.0417171733],"iteration":687,"passed_time":1.069357066,"remaining_time":0.4849409949},
{"learn":[0.04164242906],"iteration":688,"passed_time":1.071245382,"remaining_time":0.4835374654},
{"learn":[0.04155385288],"iteration":689,"passed_time":1.073002421,"remaining_time":0.4820735516},
{"learn":[0.04150473997],"iteration":690,"passed_time":1.07473826,"remaining_time":0.4805993086},
{"learn":[0.04146934998],"iteration":691,"passed_time":1.076422698,"remaining_time":0.4791014319},
{"learn":[0.04138366592],"iteration":692,"passed_time":1.078195237,"remaining_time":0.477642046},
{"learn":[0.04130703719],"iteration":693,"passed_time":1.079902099,"remaining_time":0.4761527988},
{"learn":[0.04129914477],"iteration":694,"passed_time":1.081598961,"remaining_time":0.474658537},
{"learn":[0.04123357579],"iteration":695,"passed_time":1.083300813,"remaining_time":0.4731658725},
{"learn":[0.04120706975],"iteration":696,"passed_time":1.08499504,"remaining_time":0.471669293},
{"learn":[0.04110852023],"iteration":697,"passed_time":1.086694127,"remaining_time":0.4701742498},
{"learn":[0.04102742815],"iteration":698,"passed_time":1.088425927,"remaining_time":0.4686927098},
{"learn":[0.0409258303],"iteration":699,"passed_time":1.090122589,"remaining_time":0.4671953953},
{"learn":[0.04083571474],"iteration":700,"passed_time":1.091794533,"remaining_time":0.465686969},
{"learn":[0.04076090893],"iteration":701,"passed_time":1.093503619,"remaining_time":0.4641938439},
{"learn":[0.04074852911],"iteration":702,"passed_time":1.095156846,"remaining_time":0.4626765053},
{"learn":[0.04065987951],"iteration":703,"passed_time":1.096869238,"remaining_time":0.461183657},
{"learn":[0.04064651143],"iteration":704,"passed_time":1.098625493,"remaining_time":0.4597085396},
{"learn":[0.04061085111],"iteration":705,"passed_time":1.100301424,"remaining_time":0.4581991767},
{"learn":[0.0404933103],"iteration":706,"passed_time":1.101905646,"remaining_time":0.456659624},
{"learn":[0.04043903507],"iteration":707,"passed_time":1.103445361,"remaining_time":0.4550932845},
{"learn":[0.0403872626],"iteration":708,"passed_time":1.104983063,"remaining_time":0.4535261936},
{"learn":[0.04032781645],"iteration":709,"passed_time":1.106521075,"remaining_time":0.4519593122},
{"learn":[0.04029310763],"iteration":710,"passed_time":1.108040511,"remaining_time":0.4503849614},
{"learn":[0.04020925458],"iteration":711,"passed_time":1.109701593,"remaining_time":0.4488680601},
{"learn":[0.04013741315],"iteration":712,"passed_time":1.111298159,"remaining_time":0.4473247851},
{"learn":[0.0400755868],"iteration":713,"passed_time":1.112863405,"remaining_time":0.4457688148},
{"learn":[0.03998771809],"iteration":714,"passed_time":1.114528575,"remaining_time":0.4442526488},
{"learn":[0.03993424451],"iteration":715,"passed_time":1.116132225,"remaining_time":0.4427116648},
{"learn":[0.03990068064],"iteration":716,"passed_time":1.11767333,"remaining_time":0.4411458192},
{"learn":[0.0398218402],"iteration":717,"passed_time":1.119168378,"remaining_time":0.4395619536},
{"learn":[0.03976898069],"iteration":718,"passed_time":1.120643638,"remaining_time":0.4379706012},
{"learn":[0.03969653752],"iteration":719,"passed_time":1.122157333,"remaining_time":0.4363945182},
{"learn":[0.03960606327],"iteration":720,"passed_time":1.123612022,"remaining_time":0.4347957755},
{"learn":[0.03957177363],"iteration":721,"passed_time":1.125061281,"remaining_time":0.4331953409},
{"learn":[0.03952600442],"iteration":722,"passed_time":1.126534917,"remaining_time":0.4316046641},
{"learn":[0.03945591347],"iteration":723,"passed_time":1.128039755,"remaining_time":0.4300262049},
{"learn":[0.03945018325],"iteration":724,"passed_time":1.129594089,"remaining_time":0.4284667233},
{"learn":[0.03937844312],"iteration":725,"passed_time":1.131138173,"remaining_time":0.4269033875},
{"learn":[0.03932709194],"iteration":726,"passed_time":1.132608042,"remaining_time":0.4253122358},
{"learn":[0.03927217848],"iteration":727,"passed_time":1.134125273,"remaining_time":0.4237391132},
{"learn":[0.03921154288],"iteration":728,"passed_time":1.135585885,"remaining_time":0.4221450956},
{"learn":[0.03916129895],"iteration":729,"passed_time":1.136990206,"remaining_time":0.420530624},
{"learn":[0.03903978328],"iteration":730,"passed_time":1.13852746,"remaining_time":0.4189656453},
{"learn":[0.03896539726],"iteration":731,"passed_time":1.140029832,"remaining_time":0.4173879714},
{"learn":[0.03893122401],"iteration":732,"passed_time":1.141474843,"remaining_time":0.4157896086},
{"learn":[0.03885384831],"iteration":733,"passed_time":1.142987906,"remaining_time":0.4142163258},
{"learn":[0.03879433182],"iteration":734,"passed_time":1.14452171,"remaining_time":0.4126506847},
{"learn":[0.03875587487],"iteration":735,"passed_time":1.146024604,"remaining_time":0.4110740427},
{"learn":[0.03868524608],"iteration":736,"passed_time":1.147493672,"remaining_time":0.40948553},
{"learn":[0.03863989319],"iteration":737,"passed_time":1.148965545,"remaining_time":0.4078983369},
{"learn":[0.03857045098],"iteration":738,"passed_time":1.150466184,"remaining_time":0.4063216156},
{"learn":[0.03853758723],"iteration":739,"passed_time":1.151957936,"remaining_time":0.4047419774},
{"learn":[0.03845905427],"iteration":740,"passed_time":1.153459106,"remaining_time":0.4031658683},
{"learn":[0.03834989856],"iteration":741,"passed_time":1.154976458,"remaining_time":0.4015955877},
{"learn":[0.03825903755],"iteration":742,"passed_time":1.156507346,"remaining_time":0.4000301317},
{"learn":[0.0382531945],"iteration":743,"passed_time":1.158012354,"remaining_time":0.3984558636},
{"learn":[0.03820003399],"iteration":744,"passed_time":1.159666462,"remaining_time":0.3969328159},
{"learn":[0.03816776151],"iteration":745,"passed_time":1.161233461,"remaining_time":0.3953797575},
{"learn":[0.0381228223],"iteration":746,"passed_time":1.162773227,"remaining_time":0.3938174382},
{"learn":[0.03805803324],"iteration":747,"passed_time":1.164365064,"remaining_time":0.392272722},
{"learn":[0.03797639154],"iteration":748,"passed_time":1.16592045,"remaining_time":0.3907156647},
{"learn":[0.0379280129],"iteration":749,"passed_time":1.167435768,"remaining_time":0.3891452559},
{"learn":[0.03787843571],"iteration":750,"passed_time":1.168872472,"remaining_time":0.3875489288},
{"learn":[0.03783818814],"iteration":751,"passed_time":1.170334546,"remaining_time":0.3859613928},
{"learn":[0.03780412323],"iteration":752,"passed_time":1.171829775,"remaining_time":0.3843850655},
{"learn":[0.03777564974],"iteration":753,"passed_time":1.173311918,"remaining_time":0.382804684},
{"learn":[0.03773526415],"iteration":754,"passed_time":1.174916957,"remaining_time":0.381264443},
{"learn":[0.03767573253],"iteration":755,"passed_time":1.176493738,"remaining_time":0.3797149103},
{"learn":[0.03763836791],"iteration":756,"passed_time":1.178625179,"remaining_time":0.3783433533},
{"learn":[0.03758744782],"iteration":757,"passed_time":1.180185635,"remaining_time":0.3767874982},
{"learn":[0.03755566381],"iteration":758,"passed_time":1.181964287,"remaining_time":0.3753009132},
{"learn":[0.03743657201],"iteration":759,"passed_time":1.183429607,"remaining_time":0.3737146127},
{"learn":[0.03738371239],"iteration":760,"passed_time":1.184963147,"remaining_time":0.3721500553},
{"learn":[0.03733103968],"iteration":761,"passed_time":1.186495508,"remaining_time":0.3705852111},
{"learn":[0.03729009335],"iteration":762,"passed_time":1.188067967,"remaining_time":0.3690329073},
{"learn":[0.03724984687],"iteration":763,"passed_time":1.189685254,"remaining_time":0.3674943979},
{"learn":[0.03719905845],"iteration":764,"passed_time":1.191314508,"remaining_time":0.3659593586},
{"learn":[0.03716829498],"iteration":765,"passed_time":1.193030427,"remaining_time":0.3644505483},
{"learn":[0.03714172402],"iteration":766,"passed_time":1.194677202,"remaining_time":0.362920193},
{"learn":[0.03706883432],"iteration":767,"passed_time":1.196287161,"remaining_time":0.3613784132},
{"learn":[0.03701873663],"iteration":768,"passed_time":1.197848472,"remaining_time":0.3598218427},
{"learn":[0.03701392507],"iteration":769,"passed_time":1.199366635,"remaining_time":0.3582523716},
{"learn":[0.03694258621],"iteration":770,"passed_time":1.200858167,"remaining_time":0.3566751234},
{"learn":[0.03689239684],"iteration":771,"passed_time":1.202419865,"remaining_time":0.3551188203},
{"learn":[0.03683939829],"iteration":772,"passed_time":1.204059352,"remaining_time":0.3535853465},
{"learn":[0.03681346835],"iteration":773,"passed_time":1.205662525,"remaining_time":0.3520409956},
{"learn":[0.03680853781],"iteration":774,"passed_time":1.207129498,"remaining_time":0.350456951},
{"learn":[0.03678493343],"iteration":775,"passed_time":1.208592023,"remaining_time":0.3488719241},
{"learn":[0.03672662045],"iteration":776,"passed_time":1.210105497,"remaining_time":0.3473018351},
{"learn":[0.03666519663],"iteration":777,"passed_time":1.211529627,"remaining_time":0.3457063974},
{"learn":[0.03658208434],"iteration":778,"passed_time":1.21301707,"remaining_time":0.3441293614},
{"learn":[0.03652123604],"iteration":779,"passed_time":1.214663163,"remaining_time":0.3425973025},
{"learn":[0.0364856159],"iteration":780,"passed_time":1.216150998,"remaining_time":0.3410205742},
{"learn":[0.03647063419],"iteration":781,"passed_time":1.217590447,"remaining_time":0.3394305851},
{"learn":[0.03641098019],"iteration":782,"passed_time":1.219112809,"remaining_time":0.3378639586},
{"learn":[0.03638926405],"iteration":783,"passed_time":1.220562409,"remaining_time":0.3362773983},
{"learn":[0.03632413579],"iteration":784,"passed_time":1.222047237,"remaining_time":0.3347008356},
{"learn":[0.03624932027],"iteration":785,"passed_time":1.223580105,"remaining_time":0.333137586},
{"learn":[0.03615730928],"iteration":786,"passed_time":1.225109491,"remaining_time":0.3315734708},
{"learn":[0.03614128226],"iteration":787,"passed_time":1.226550534,"remaining_time":0.3299856765},
{"learn":[0.0360649845],"iteration":788,"passed_time":1.2279881,"remaining_time":0.3283973245},
{"learn":[0.03602300934],"iteration":789,"passed_time":1.229423341,"remaining_time":0.3268087363},
{"learn":[0.03592624923],"iteration":790,"passed_time":1.230920003,"remaining_time":0.3252367643},
{"learn":[0.03585077116],"iteration":791,"passed_time":1.232403348,"remaining_time":0.3236614853},
{"learn":[0.03584585064],"iteration":792,"passed_time":1.233856935,"remaining_time":0.3220786704},
{"learn":[0.03576784454],"iteration":793,"passed_time":1.235335111,"remaining_time":0.3205025602},
{"learn":[0.03572933919],"iteration":794,"passed_time":1.236852843,"remaining_time":0.3189368967},
{"learn":[0.03567140962],"iteration":795,"passed_time":1.238338674,"remaining_time":0.3173631776},
{"learn":[0.03563398738],"iteration":796,"passed_time":1.23983811,"remaining_time":0.3157931448},
{"learn":[0.03560598951],"iteration":797,"passed_time":1.241342457,"remaining_time":0.3142245317},
{"learn":[0.03553698044],"iteration":798,"passed_time":1.242836213,"remaining_time":0.3126534152},
{"learn":[0.03547166016],"iteration":799,"passed_time":1.244394604,"remaining_time":0.3110986511},
{"learn":[0.03539611404],"iteration":800,"passed_time":1.245981375,"remaining_time":0.3095509284},
{"learn":[0.03533071646],"iteration":801,"passed_time":1.247528024,"remaining_time":0.307993203},
{"learn":[0.03529383463],"iteration":802,"passed_time":1.249268141,"remaining_time":0.3064829686},
{"learn":[0.03522521375],"iteration":803,"passed_time":1.250879937,"remaining_time":0.3049408802},
{"learn":[0.03518248458],"iteration":804,"passed_time":1.252472516,"remaining_time":0.3033939634},
{"learn":[0.03513007286],"iteration":805,"passed_time":1.253966532,"remaining_time":0.3018232099},
{"learn":[0.03511560382],"iteration":806,"passed_time":1.255495947,"remaining_time":0.3002611125},
{"learn":[0.0350502203],"iteration":807,"passed_time":1.257084004,"remaining_time":0.2987130306},
{"learn":[0.03497143684],"iteration":808,"passed_time":1.258601088,"remaining_time":0.2971480938},
{"learn":[0.03491292126],"iteration":809,"passed_time":1.260116496,"remaining_time":0.2955828819},
{"learn":[0.03488698524],"iteration":810,"passed_time":1.261591035,"remaining_time":0.2940082682},
{"learn":[0.03486670449],"iteration":811,"passed_time":1.263108233,"remaining_time":0.292443778},
{"learn":[0.03481812923],"iteration":812,"passed_time":1.264644301,"remaining_time":0.2908837445},
{"learn":[0.03475989862],"iteration":813,"passed_time":1.26617363,"remaining_time":0.2893222299},
{"learn":[0.03471424852],"iteration":814,"passed_time":1.267694538,"remaining_time":0.2877588829},
{"learn":[0.03466281054],"iteration":815,"passed_time":1.269223763,"remaining_time":0.2861975153},
{"learn":[0.03465791077],"iteration":816,"passed_time":1.270664466,"remaining_time":0.284616398},
{"learn":[0.03461260646],"iteration":817,"passed_time":1.272116831,"remaining_time":0.283038219},
{"learn":[0.0345272559],"iteration":818,"passed_time":1.273564346,"remaining_time":0.2814592755},
{"learn":[0.03447168381],"iteration":819,"passed_time":1.275024306,"remaining_time":0.2798833842},
{"learn":[0.03440844251],"iteration":820,"passed_time":1.27652237,"remaining_time":0.2783160831},
{"learn":[0.03438293213],"iteration":821,"passed_time":1.278066173,"remaining_time":0.2767588551},
{"learn":[0.03432888761],"iteration":822,"passed_time":1.279475184,"remaining_time":0.2751726701},
{"learn":[0.03427214324],"iteration":823,"passed_time":1.280987606,"remaining_time":0.2736090032},
{"learn":[0.03425219243],"iteration":824,"passed_time":1.282430442,"remaining_time":0.2720306999},
{"learn":[0.03423041288],"iteration":825,"passed_time":1.283901313,"remaining_time":0.2704586302},
{"learn":[0.03417202225],"iteration":826,"passed_time":1.285407483,"remaining_time":0.2688941894},
{"learn":[0.03413380459],"iteration":827,"passed_time":1.286974662,"remaining_time":0.2673425627},
{"learn":[0.03412105016],"iteration":828,"passed_time":1.28848982,"remaining_time":0.2657801679},
{"learn":[0.0341168832],"iteration":829,"passed_time":1.290009326,"remaining_time":0.2642187776},
{"learn":[0.03409016483],"iteration":830,"passed_time":1.291535435,"remaining_time":0.2626588309},
{"learn":[0.03401429146],"iteration":831,"passed_time":1.293234351,"remaining_time":0.2611338593},
{"learn":[0.03397662376],"iteration":832,"passed_time":1.29475561,"remaining_time":0.2595728535},
{"learn":[0.03397251313],"iteration":833,"passed_time":1.296294765,"remaining_time":0.2580155047},
{"learn":[0.03388805381],"iteration":834,"passed_time":1.297800764,"remaining_time":0.2564516481},
{"learn":[0.03378237042],"iteration":835,"passed_time":1.299367563,"remaining_time":0.2548998568},
{"learn":[0.03374355078],"iteration":836,"passed_time":1.30090807,"remaining_time":0.2533429096},
{"learn":[0.0336578287],"iteration":837,"passed_time":1.302368921,"remaining_time":0.2517706029},
{"learn":[0.03365380283],"iteration":838,"passed_time":1.303796017,"remaining_time":0.2501920843},
{"learn":[0.03364421956],"iteration":839,"passed_time":1.305308629,"remaining_time":0.2486302151},
{"learn":[0.03358604084],"iteration":840,"passed_time":1.306810471,"remaining_time":0.2470664267},
{"learn":[0.03352206069],"iteration":841,"passed_time":1.308281643,"remaining_time":0.2454970303},
{"learn":[0.03351829365],"iteration":842,"passed_time":1.309719149,"remaining_time":0.2439215971},
{"learn":[0.03349602778],"iteration":843,"passed_time":1.311234406,"remaining_time":0.2423608618},
{"learn":[0.03345241022],"iteration":844,"passed_time":1.3126966,"remaining_time":0.2407905007},
{"learn":[0.03340878562],"iteration":845,"passed_time":1.314201508,"remaining_time":0.2392281705},
{"learn":[0.03339233679],"iteration":846,"passed_time":1.31563715,"remaining_time":0.237653464},
{"learn":[0.03338793855],"iteration":847,"passed_time":1.317142849,"remaining_time":0.2360916428},
{"learn":[0.03333737192],"iteration":848,"passed_time":1.318707323,"remaining_time":0.2345404073},
{"learn":[0.0333338291],"iteration":849,"passed_time":1.320199506,"remaining_time":0.2329763834},
{"learn":[0.03331356063],"iteration":850,"passed_time":1.321697079,"remaining_time":0.2314134721},
{"learn":[0.03327260018],"iteration":851,"passed_time":1.323301371,"remaining_time":0.2298692522},
{"learn":[0.03322443732],"iteration":852,"passed_time":1.324881084,"remaining_time":0.2283206558},
{"learn":[0.03320853562],"iteration":853,"passed_time":1.326409648,"remaining_time":0.2267632419},
{"learn":[0.03316545459],"iteration":854,"passed_time":1.32790156,"remaining_time":0.2251996797},
{"learn":[0.03310215778],"iteration":855,"passed_time":1.329450453,"remaining_time":0.2236458706},
{"learn":[0.03305110638],"iteration":856,"passed_time":1.330961573,"remaining_time":0.22208577},
{"learn":[0.03297961439],"iteration":857,"passed_time":1.332458745,"remaining_time":0.2205234753},
{"learn":[0.03291096774],"iteration":858,"passed_time":1.333919276,"remaining_time":0.2189553177},
{"learn":[0.03290711839],"iteration":859,"passed_time":1.335401479,"remaining_time":0.2173909385},
{"learn":[0.0328513941],"iteration":860,"passed_time":1.336880416,"remaining_time":0.2158262228},
{"learn":[0.03279811969],"iteration":861,"passed_time":1.338535868,"remaining_time":0.2142899649},
{"learn":[0.03278900427],"iteration":862,"passed_time":1.340274755,"remaining_time":0.2127666761},
{"learn":[0.03274370683],"iteration":863,"passed_time":1.342145667,"remaining_time":0.2112636698},
{"learn":[0.03272347849],"iteration":864,"passed_time":1.343918017,"remaining_time":0.2097444304},
{"learn":[0.03271144923],"iteration":865,"passed_time":1.345673934,"remaining_time":0.2082220637},
{"learn":[0.03268678719],"iteration":866,"passed_time":1.347366809,"remaining_time":0.2066894874},
{"learn":[0.03263413358],"iteration":867,"passed_time":1.349089862,"remaining_time":0.2051611311},
{"learn":[0.03256835248],"iteration":868,"passed_time":1.350804619,"remaining_time":0.2036310761},
{"learn":[0.03249891897],"iteration":869,"passed_time":1.352783969,"remaining_time":0.2021401333},
{"learn":[0.03246031235],"iteration":870,"passed_time":1.354541269,"remaining_time":0.2006151822},
{"learn":[0.03238871989],"iteration":871,"passed_time":1.356270574,"remaining_time":0.1990855889},
{"learn":[0.0323541032],"iteration":872,"passed_time":1.35801518,"remaining_time":0.1975577639},
{"learn":[0.032273098],"iteration":873,"passed_time":1.35971097,"remaining_time":0.1960224053},
{"learn":[0.03222512537],"iteration":874,"passed_time":1.361408493,"remaining_time":0.1944869276},
{"learn":[0.03217359276],"iteration":875,"passed_time":1.363127148,"remaining_time":0.1929540712},
{"learn":[0.03214795723],"iteration":876,"passed_time":1.364904749,"remaining_time":0.1914290582},
{"learn":[0.03214450355],"iteration":877,"passed_time":1.367047762,"remaining_time":0.1899542448},
{"learn":[0.03212388327],"iteration":878,"passed_time":1.36933182,"remaining_time":0.1884973268},
{"learn":[0.03207746316],"iteration":879,"passed_time":1.371742646,"remaining_time":0.1870558153},
{"learn":[0.03201556762],"iteration":880,"passed_time":1.374473737,"remaining_time":0.1856553629},
{"learn":[0.03199459577],"iteration":881,"passed_time":1.376435085,"remaining_time":0.1841489116},
{"learn":[0.03194197134],"iteration":882,"passed_time":1.381691614,"remaining_time":0.1830780507},
{"learn":[0.03190295587],"iteration":883,"passed_time":1.383738409,"remaining_time":0.1815765333},
{"learn":[0.03183854993],"iteration":884,"passed_time":1.385516007,"remaining_time":0.1800388032},
{"learn":[0.03183526346],"iteration":885,"passed_time":1.386958433,"remaining_time":0.1784574056},
{"learn":[0.03175391768],"iteration":886,"passed_time":1.388469092,"remaining_time":0.1768850139},
{"learn":[0.03171067203],"iteration":887,"passed_time":1.389950573,"remaining_time":0.1753090813},
{"learn":[0.03165084973],"iteration":888,"passed_time":1.391437325,"remaining_time":0.1737340193},
{"learn":[0.03162701406],"iteration":889,"passed_time":1.392918517,"remaining_time":0.1721584684},
{"learn":[0.03156583625],"iteration":890,"passed_time":1.394358688,"remaining_time":0.1705781111},
{"learn":[0.03154287054],"iteration":891,"passed_time":1.395834729,"remaining_time":0.1690024111},
{"learn":[0.03149391718],"iteration":892,"passed_time":1.39760097,"remaining_time":0.1674617064},
{"learn":[0.03149091349],"iteration":893,"passed_time":1.399135996,"remaining_time":0.1658930824},
{"learn":[0.03144240418],"iteration":894,"passed_time":1.400650974,"remaining_time":0.1643221813},
{"learn":[0.03141770983],"iteration":895,"passed_time":1.402152414,"remaining_time":0.1627498338},
{"learn":[0.03141346122],"iteration":896,"passed_time":1.403600441,"remaining_time":0.161171511},
{"learn":[0.03135116212],"iteration":897,"passed_time":1.405105829,"remaining_time":0.159599994},
{"learn":[0.0313059464],"iteration":898,"passed_time":1.406587712,"remaining_time":0.1580259832},
{"learn":[0.03125290414],"iteration":899,"passed_time":1.408109061,"remaining_time":0.1564565624},
{"learn":[0.03119741403],"iteration":900,"passed_time":1.409637305,"remaining_time":0.1548880057},
{"learn":[0.03119499278],"iteration":901,"passed_time":1.411127553,"remaining_time":0.1533154105},
{"learn":[0.03118688556],"iteration":902,"passed_time":1.412672509,"remaining_time":0.1517488742},
{"learn":[0.03118397951],"iteration":903,"passed_time":1.41409716,"remaining_time":0.1501696099},
{"learn":[0.03114143587],"iteration":904,"passed_time":1.415567861,"remaining_time":0.1485955213},
{"learn":[0.03109999321],"iteration":905,"passed_time":1.417330151,"remaining_time":0.1470519141},
{"learn":[0.03106441301],"iteration":906,"passed_time":1.41932764,"remaining_time":0.145531941},
{"learn":[0.03103642682],"iteration":907,"passed_time":1.420971118,"remaining_time":0.1439750472},
{"learn":[0.03097049201],"iteration":908,"passed_time":1.422583054,"remaining_time":0.1424148052},
{"learn":[0.03093043396],"iteration":909,"passed_time":1.424064656,"remaining_time":0.1408415594},
{"learn":[0.03086381929],"iteration":910,"passed_time":1.42555739,"remaining_time":0.1392696023},
{"learn":[0.03082396611],"iteration":911,"passed_time":1.42710444,"remaining_time":0.13770306},
{"learn":[0.03077293875],"iteration":912,"passed_time":1.428630468,"remaining_time":0.1361345572},
{"learn":[0.03075925042],"iteration":913,"passed_time":1.43014752,"remaining_time":0.1345653027},
{"learn":[0.03072804331],"iteration":914,"passed_time":1.431623681,"remaining_time":0.1329923638},
{"learn":[0.03068516802],"iteration":915,"passed_time":1.433108279,"remaining_time":0.1314204099},
{"learn":[0.03068102968],"iteration":916,"passed_time":1.43457387,"remaining_time":0.129846926},
{"learn":[0.0306585646],"iteration":917,"passed_time":1.436065191,"remaining_time":0.1282759756},
{"learn":[0.03061472414],"iteration":918,"passed_time":1.437553967,"remaining_time":0.1267049742},
{"learn":[0.03057868788],"iteration":919,"passed_time":1.439018095,"remaining_time":0.1251320082},
{"learn":[0.03057544926],"iteration":920,"passed_time":1.440459999,"remaining_time":0.1235573723},
{"learn":[0.03050886161],"iteration":921,"passed_time":1.442434573,"remaining_time":0.1220280876},
{"learn":[0.03042933123],"iteration":922,"passed_time":1.443955582,"remaining_time":0.1204599998},
{"learn":[0.03039208731],"iteration":923,"passed_time":1.445484517,"remaining_time":0.1188926659},
{"learn":[0.03033299311],"iteration":924,"passed_time":1.446940709,"remaining_time":0.117319517},
{"learn":[0.03031189464],"iteration":925,"passed_time":1.448412282,"remaining_time":0.1157478497},
{"learn":[0.03023995338],"iteration":926,"passed_time":1.44992253,"remaining_time":0.1141794441},
{"learn":[0.0301838347],"iteration":927,"passed_time":1.451416185,"remaining_time":0.1126098764},
{"learn":[0.03013367653],"iteration":928,"passed_time":1.452877347,"remaining_time":0.1110379889},
{"learn":[0.03010096705],"iteration":929,"passed_time":1.454352757,"remaining_time":0.1094674118},
{"learn":[0.03009761375],"iteration":930,"passed_time":1.455841012,"remaining_time":0.1078979912},
{"learn":[0.03004588204],"iteration":931,"passed_time":1.45738218,"remaining_time":0.1063326054},
{"learn":[0.02996614563],"iteration":932,"passed_time":1.458936825,"remaining_time":0.1047682393},
{"learn":[0.02995321473],"iteration":933,"passed_time":1.460431853,"remaining_time":0.1031996813},
{"learn":[0.02991318099],"iteration":934,"passed_time":1.46192076,"remaining_time":0.1016308549},
{"learn":[0.0298671602],"iteration":935,"passed_time":1.463442029,"remaining_time":0.1000644122},
{"learn":[0.02981132414],"iteration":936,"passed_time":1.465023787,"remaining_time":0.09850213293},
{"learn":[0.02975232961],"iteration":937,"passed_time":1.466531089,"remaining_time":0.09693489073},
{"learn":[0.02970885959],"iteration":938,"passed_time":1.468054382,"remaining_time":0.09536881503},
{"learn":[0.02967351705],"iteration":939,"passed_time":1.469583417,"remaining_time":0.09380319681},
{"learn":[0.02963474223],"iteration":940,"passed_time":1.471209371,"remaining_time":0.09224373312},
{"learn":[0.02960160719],"iteration":941,"passed_time":1.4727563,"remaining_time":0.09067926264},
{"learn":[0.02959704504],"iteration":942,"passed_time":1.474254414,"remaining_time":0.0891118787},
{"learn":[0.02956860344],"iteration":943,"passed_time":1.475724043,"remaining_time":0.0875429517},
{"learn":[0.02954800411],"iteration":944,"passed_time":1.477176428,"remaining_time":0.08597323126},
{"learn":[0.02949427959],"iteration":945,"passed_time":1.478678009,"remaining_time":0.08440656711},
{"learn":[0.02946570531],"iteration":946,"passed_time":1.480158659,"remaining_time":0.08283886899},
{"learn":[0.02941380425],"iteration":947,"passed_time":1.481628979,"remaining_time":0.08127078789},
{"learn":[0.02936206262],"iteration":948,"passed_time":1.483138125,"remaining_time":0.07970499934},
{"learn":[0.02930582802],"iteration":949,"passed_time":1.484595991,"remaining_time":0.07813663109},
{"learn":[0.02927749743],"iteration":950,"passed_time":1.486198629,"remaining_time":0.07657595459},
{"learn":[0.02921545263],"iteration":951,"passed_time":1.487755899,"remaining_time":0.07501290245},
{"learn":[0.02920892555],"iteration":952,"passed_time":1.489328148,"remaining_time":0.07345060119},
{"learn":[0.02919201615],"iteration":953,"passed_time":1.490867823,"remaining_time":0.07188670845},
{"learn":[0.02912823307],"iteration":954,"passed_time":1.492409172,"remaining_time":0.07032294526},
{"learn":[0.02906570989],"iteration":955,"passed_time":1.493951713,"remaining_time":0.06875928384},
{"learn":[0.02899644949],"iteration":956,"passed_time":1.495503792,"remaining_time":0.06719609516},
{"learn":[0.02899397992],"iteration":957,"passed_time":1.496999732,"remaining_time":0.06563046843},
{"learn":[0.02895940849],"iteration":958,"passed_time":1.498615586,"remaining_time":0.0640701137},
{"learn":[0.02891023187],"iteration":959,"passed_time":1.500143719,"remaining_time":0.0625059883},
{"learn":[0.02883567465],"iteration":960,"passed_time":1.501855961,"remaining_time":0.06094940946},
{"learn":[0.0288327862],"iteration":961,"passed_time":1.503342834,"remaining_time":0.05938360466},
{"learn":[0.0288305663],"iteration":962,"passed_time":1.504789337,"remaining_time":0.05781641275},
{"learn":[0.02878225219],"iteration":963,"passed_time":1.506293303,"remaining_time":0.05625161712},
{"learn":[0.0287529535],"iteration":964,"passed_time":1.507734346,"remaining_time":0.05468466539},
{"learn":[0.02874432984],"iteration":965,"passed_time":1.509184587,"remaining_time":0.05311829808},
{"learn":[0.02871676433],"iteration":966,"passed_time":1.510668593,"remaining_time":0.05155332324},
{"learn":[0.02866463588],"iteration":967,"passed_time":1.512191285,"remaining_time":0.04998979456},
{"learn":[0.02865027569],"iteration":968,"passed_time":1.513578323,"remaining_time":0.04842201033},
{"learn":[0.02860916599],"iteration":969,"passed_time":1.515049424,"remaining_time":0.04685719869},
{"learn":[0.02856662441],"iteration":970,"passed_time":1.516667212,"remaining_time":0.04529696103},
{"learn":[0.02854541014],"iteration":971,"passed_time":1.518184905,"remaining_time":0.04373372154},
{"learn":[0.02848409638],"iteration":972,"passed_time":1.519708318,"remaining_time":0.04217073443},
{"learn":[0.028440814],"iteration":973,"passed_time":1.521190461,"remaining_time":0.0406067269},
{"learn":[0.02840873575],"iteration":974,"passed_time":1.522657114,"remaining_time":0.03904249011},
{"learn":[0.02837374817],"iteration":975,"passed_time":1.524152563,"remaining_time":0.03747916139},
{"learn":[0.02831888086],"iteration":976,"passed_time":1.525718871,"remaining_time":0.03591763974},
{"learn":[0.02828713382],"iteration":977,"passed_time":1.527296517,"remaining_time":0.03435636336},
{"learn":[0.02825050956],"iteration":978,"passed_time":1.528849338,"remaining_time":0.03279452103},
{"learn":[0.02819064607],"iteration":979,"passed_time":1.530480886,"remaining_time":0.0312343038},
{"learn":[0.02815128226],"iteration":980,"passed_time":1.532128111,"remaining_time":0.02967424477},
{"learn":[0.02808832251],"iteration":981,"passed_time":1.533721952,"remaining_time":0.02811302968},
{"learn":[0.0280385577],"iteration":982,"passed_time":1.535265565,"remaining_time":0.02655087957},
{"learn":[0.02800281601],"iteration":983,"passed_time":1.536789109,"remaining_time":0.0249884408},
{"learn":[0.02797643922],"iteration":984,"passed_time":1.538306321,"remaining_time":0.02342598458},
{"learn":[0.02797380418],"iteration":985,"passed_time":1.539768295,"remaining_time":0.02186283583},
{"learn":[0.02797018095],"iteration":986,"passed_time":1.541232934,"remaining_time":0.02029992719},
{"learn":[0.02792909577],"iteration":987,"passed_time":1.542682964,"remaining_time":0.01873704005},
{"learn":[0.02790333674],"iteration":988,"passed_time":1.544196468,"remaining_time":0.01717508711},
{"learn":[0.02786432048],"iteration":989,"passed_time":1.545704211,"remaining_time":0.01561317385},
{"learn":[0.02782772839],"iteration":990,"passed_time":1.547262072,"remaining_time":0.01405182507},
{"learn":[0.02780409865],"iteration":991,"passed_time":1.548791698,"remaining_time":0.01249025563},
{"learn":[0.02777553756],"iteration":992,"passed_time":1.550316013,"remaining_time":0.01092871308},
{"learn":[0.02771882736],"iteration":993,"passed_time":1.551840679,"remaining_time":0.009367247562},
{"learn":[0.02769279734],"iteration":994,"passed_time":1.553369393,"remaining_time":0.007805876349},
{"learn":[0.02769043818],"iteration":995,"passed_time":1.554836287,"remaining_time":0.006244322436},
{"learn":[0.02763172709],"iteration":996,"passed_time":1.556381072,"remaining_time":0.004683192794},
{"learn":[0.02758661751],"iteration":997,"passed_time":1.557884416,"remaining_time":0.003122012859},
{"learn":[0.02755496275],"iteration":998,"passed_time":1.559367061,"remaining_time":0.001560927989},
{"learn":[0.02750275599],"iteration":999,"passed_time":1.560906055,"remaining_time":0}
]}